{"slug":"airlines","wics_1st":"산업재","wics_2nd":"운송","wics_3rd":"항공사","trading_date":"2026-06-26","previous_trading_date":"2026-06-25","display_date":"2026-06-29","generated_at":"2026-06-29T06:52:13","sector_return":-3.8,"ai_summary":["대한항공-아시아나 합병 최종 인가, 12월 17일 통합 출범 확정","대한항공, 아시아나 적자 흡수 및 통합 시너지 창출이 핵심 과제"],"news":[{"id":"bf4e33c10ac5","title":"대한항공-아시아나항공 합병 인가…12월 17일 대한항공 통합","summary":"국토교통부는 대한항공이 자회사인 아시아나항공과 합병하고자 신청한 법인 합병 건과 관련해 ‘항공사업법’에 따른 엄격한 심사를 거쳐 합병을 인가했다고 밝혔다.\n\n대한항공은 이후 국토부 장관의 합병 인가를 신청했다.\n\n국토부는 관련 법령에 따른 심사 결과, 합병을 조건부 인가하기로 결정했다.","keyword":"대한항공 합병","url":"https://zdnet.co.kr/view/?no=20260626143116","source":"","published_at":"2026-06-26T14:32:14","sentiment":"positive","source_type":"news","is_new":true},{"id":"01655cb71e54","title":"대한항공, 합병인가 넘어도 과제 산적…아시아나 '적자 흡수' 돌파구는","summary":"대한항공 연결 매출액은 2024년 1분기 4조2914억원에서 2025년 6조4919억원, 2026년 6조6581억원으로 커졌다.\n\nLS증권은 대한항공 연결 영업이익을 2026년 5080억원, 2027년 2조1880억원으로 추정했다.\n\n1분기 아시아나 별도 화물노선 수익은 2025년 3709억원에서 2026년 620억원으로 줄었다.","keyword":"실적 추정","url":"https://www.bloter.net/news/articleView.html?idxno=666677","source":"","published_at":"2026-06-26T16:54:00","sentiment":"neutral","source_type":"news","is_new":true},{"id":"b8509c6cea7c","title":"제주항공 ‘인천-제주’ 정기편 10월24일까지 운항","summary":"국토부, 사업계획 변경 인가 제주항공의 ‘인천-제주’ 정기편이 10월 24일까지 운항하게 됐다.\n\n국토교통부는 제주항공이 요청한 인천-제주 국내선 정기편을 올 하계시즌이 종료되는 10월 24일까지 계속 운항하기 위해 신청한 사업계획 변경을 인가했다고 26일 밝혔다.\n\n국토부는 인천-제주 노선이 수도권과 제주를 연결하는 기존 국내선 수요는 물론, 인천국제공항을 이용하는 해외관광객과 환승객 수요를 흡수하며 안정적으로 정착하고 있는 것으로 평가했다.","keyword":"정기편 운항","url":"https://biz.heraldcorp.com/article/10789650","source":"","published_at":"2026-06-26T15:30:00","sentiment":"positive","source_type":"news","is_new":true},{"id":"f98a6582ce03","title":"티웨이항공, 다음달 6일까지 B737 신입 부기장 채용","summary":"티웨이항공이 다음달 6일 14시까지 티웨이항공 공식 채용 사이트를 통해 B737 신입 부기장을 채용한다고 28일 밝혔다.\n\n마지막으로 국내 유효한 항공무선통신사 자격증 소지자, JET 한정 자격 소지자로 JET 자격의 경우 입사 전까지 취득 조건으로 지원 가능하다.\n\n티웨이항공 B737 신입 부기장 채용 접수는 내달 6일 월요일 14시까지이며, 자세한 응시 자격과 전형 일정, 단계별 결과 발표는 공식 채용 사이트에서 할 예정이다.","keyword":"신입 부기장 채용","url":"https://news.tvchosun.com/site/data/html_dir/2026/06/28/2026062890076.html","source":"TV조선","published_at":"2026-06-28 14:01:00","sentiment":"neutral","source_type":"news","is_new":true},{"id":"901596e4f684","title":"대한항공, 여름 성수기 제주행 마일리지 특별기 띄운다","summary":"대한항공은 여름 휴가철 성수기인 7월27일부터 8월6일까지 김포∼제주 노선에 마일리지 특별기를 운항한다.\n\n대한항공은 이 기간 8월2일 하루를 제외하고 매일 2편씩 총 20편의 특별기를 운항한다고 28일 밝혔다.\n\n뉴시스 투입되는 항공기는 에어버스 8월2일 하루를 제외하고 매일 2편씩 총 20편을 운항된다.","keyword":"마일리지 특별기","url":"https://www.segye.com/newsView/20260626506065","source":"세계일보","published_at":"2026-06-28 05:23:00","sentiment":"positive","source_type":"news","is_new":true}],"global_research":[],"us_movers":[],"us_earnings":[],"stocks":[{"code":"091810","name":"트리니티항공","market":"KSP","price":748.0,"change_pct":-5.44,"market_cap":308901174780.0,"fwd_pe":2.2874618,"fwd_pb":null,"has_chart":true,"has_new":false,"news":[],"disclosures":[{"date":"2026-06-25T20:42:32","title":"특수관계인으로부터받은담보","url":"https://dart.fss.or.kr/dsaf001/main.do?rcpNo=20260625000181","is_new":false},{"date":"2026-06-23T15:55:56","title":"특수관계인에대한사모사채발행의결","url":"https://dart.fss.or.kr/dsaf001/main.do?rcpNo=20260623000285","is_new":false},{"date":"2026-06-23T15:50:55","title":"[기재정정]주요사항보고서(자본으로인정되는채무증권발행결정)","url":"https://dart.fss.or.kr/dsaf001/main.do?rcpNo=20260623000279","is_new":false},{"date":"2026-06-22T17:48:31","title":"주요사항보고서(유상증자결정)","url":"https://dart.fss.or.kr/dsaf001/main.do?rcpNo=20260622000395","is_new":false},{"date":"2026-06-19T10:05:25","title":"동일인등출자계열회사와의상품ㆍ용역거래","url":"https://dart.fss.or.kr/dsaf001/main.do?rcpNo=20260619000079","is_new":false}],"reports":[],"consensus":{"Q":{"period":"2026년 2분기","latest":-120000000000.0,"is_new":false,"series":[{"date":"2026-05-27","value":-151000000000.0},{"date":"2026-06-11","value":-120000000000.0}]},"Y":{"period":"2026년","latest":-169000000000.0,"is_new":false,"series":[{"date":"2026-05-27","value":-178000000000.0},{"date":"2026-06-11","value":-169000000000.0}]}},"briefing":{"briefing":"이번 하락은 유상증자와 관련된 소식이 주요 원인으로 작용한 것으로 보입니다. 유상증자를 통해 조달된 자금이 운영자금으로 사용될 예정이지만, 이는 투자자들에게 불안감을 초래할 수 있습니다.","content_url":"https://www.bloter.net/news/articleView.html?idxno=666222","article_title":"트리니티항공, 800억 3자배정 유상증자…운영자금 확보","change_rate":-5.44},"stk_flow":[{"date":"2026-06-26","외인":-154260000,"개인":145934000,"기관":6075000},{"date":"2026-06-25","외인":43920000,"개인":-116604000,"기관":71859000},{"date":"2026-06-24","외인":26591000,"개인":-156794000,"기관":132055000},{"date":"2026-06-23","외인":-134210000,"개인":121634000,"기관":7901000},{"date":"2026-06-22","외인":-166938000,"개인":292041000,"기관":-138846000},{"date":"2026-06-19","외인":-44750000,"개인":-5503000,"기관":-7844000},{"date":"2026-06-18","외인":32436000,"개인":14481000,"기관":-43887000}]},{"code":"272450","name":"진에어","market":"KSP","price":5660.0,"change_pct":-4.87,"market_cap":295452000000.0,"fwd_pe":6.4075475,"fwd_pb":null,"has_chart":true,"has_new":false,"news":[],"disclosures":[],"reports":[],"consensus":{"Q":{"period":"2026년 2분기","latest":-62000000000.0,"is_new":false,"series":[{"date":"2026-05-27","value":-62000000000.0}]},"Y":{}},"briefing":{"briefing":"이번 하락은 2분기 영업적자가 불가피하다는 NH투자증권의 분석에 따른 것으로 보입니다. 하반기 여객 수요 회복과 비용 부담 완화 기대감이 있지만, 현재 주가는 이러한 긍정적인 전망이 반영되지 않은 상황입니다.","content_url":"https://biz.chosun.com/stock/stock_general/2026/06/26/ERAGTJLFJNHWDGE4JZWQ6E56XA/?utm_medium=original&utm_campaign=biz","article_title":"NH證 “진에어, 하반기 여객 수요 회복·통합 LCC 출범 기대”","change_rate":-4.87},"stk_flow":[{"date":"2026-06-26","외인":-252246000,"개인":246260000,"기관":5036000},{"date":"2026-06-25","외인":219643000,"개인":-244766000,"기관":26469000},{"date":"2026-06-24","외인":108142000,"개인":-98640000,"기관":-10391000},{"date":"2026-06-23","외인":183102000,"개인":-334722000,"기관":145727000},{"date":"2026-06-22","외인":-67359000,"개인":78508000,"기관":1313000},{"date":"2026-06-19","외인":96126000,"개인":-256329000,"기관":117894000},{"date":"2026-06-18","외인":-388231000,"개인":388899000,"기관":-3560000}]},{"code":"003490","name":"대한항공","market":"KSP","price":28050.0,"change_pct":-3.61,"market_cap":10328589541050.0,"fwd_pe":9.272527,"fwd_pb":null,"has_chart":true,"has_new":true,"news":[{"id":"1722029021526626917","title":"12월 통합 '대한항공' 출범···남은 절차·과제는","summary":"지난 25일 국토교통부가 대한항공과 아시아나항공 합병 신청 건에 대해 최종 인가한 가운데 통합 '대한항공'에 대한 관심이 높아지고 있다.\n\n주요 장거리 노선 '독과점' 우려 속 슬롯 반납과 화물사업부 매각 등을 거쳐 무려 6년여 만에 최종 인가를 받은 만큼 앞으로 양사는 오는 12월17일 출범하는 통합 '대한항공' 정식 출범까지 박차를 가한다는 목표다.\n\n26일 항공업계에 따르면, 지난 25일 국토교통부는 대한항공이 자회사인 아시아나항공 합병 신청 건에 대해 '항공사업법'에 따른 심사를 거쳐 조건부 인가했다.","url":"http://www.inews24.com/view/1980118","published_at":"2026-06-26T16:10:00","sentiment":"positive","is_new":true},{"id":"1722039811268808853","title":"대한항공, 합병인가 넘어도 과제 산적…아시아나 '적자 흡수' 돌파구는","summary":"대한항공 연결 매출액은 2024년 1분기 4조2914억원에서 2025년 6조4919억원, 2026년 6조6581억원으로 커졌다.\n\nLS증권은 대한항공 연결 영업이익을 2026년 5080억원, 2027년 2조1880억원으로 추정했다.\n\n1분기 아시아나 별도 화물노선 수익은 2025년 3709억원에서 2026년 620억원으로 줄었다.","url":"https://www.bloter.net/news/articleView.html?idxno=666677","published_at":"2026-06-26T16:54:00","sentiment":"neutral","is_new":true},{"id":"1722590904289726511","title":"대한항공, 여름 성수기 제주행 마일리지 특별기 띄운다","summary":"대한항공은 여름 휴가철 성수기인 7월27일부터 8월6일까지 김포∼제주 노선에 마일리지 특별기를 운항한다.\n\n대한항공은 이 기간 8월2일 하루를 제외하고 매일 2편씩 총 20편의 특별기를 운항한다고 28일 밝혔다.\n\n뉴시스 투입되는 항공기는 에어버스 8월2일 하루를 제외하고 매일 2편씩 총 20편을 운항된다.","url":"https://www.segye.com/newsView/20260626506065","published_at":"2026-06-28T05:23:00","sentiment":"positive","is_new":true}],"disclosures":[{"date":"2026-06-26T16:01:06","title":"임원ㆍ주요주주특정증권등소유상황보고서","url":"https://dart.fss.or.kr/dsaf001/main.do?rcpNo=20260626000524","is_new":true},{"date":"2026-06-26T07:59:29","title":"[기재정정]회사합병결정(종속회사의주요경영사항)              ","url":"https://dart.fss.or.kr/dsaf001/main.do?rcpNo=20260626800036","is_new":true},{"date":"2026-06-26T07:49:28","title":"[기재정정]주요사항보고서(회사합병결정)","url":"https://dart.fss.or.kr/dsaf001/main.do?rcpNo=20260626000005","is_new":true},{"date":"2026-06-25T21:17:28","title":"증권신고서(합병)","url":"https://dart.fss.or.kr/dsaf001/main.do?rcpNo=20260625000630","is_new":false}],"reports":[{"broker":"iM증권","title":"명확한 성장 방향성, 기업 가치도 상승할 것","url":"https://ddi-cdn.deepsearch.com/research/company/2026/06/19/1719383399283691520/000-af8697ae0aee6a2388ee2ef373dcb3a480cdcf94.pdf","date":"2026-06-19T08:59:34","summary":"iM증권은 대한항공에 대해 투자의견 Buy를 유지하고 목표주가를 기존 34,000원에서 40,000원으로 상향했다. 유가 하향 추세와 아시아나항공 합병 기일 확정(12월 16일)에 따른 투자심리 개선으로 Target EV/EBITDA 배수를 5.7배로 상향했다. 2Q26은 유가 급등으로 연결 기준 영업손실이 예상되나, 3Q26부터 유가 하락과 중동 항공사 공급 감소에 따른 환승 수요 증가로 호실적이 전망된다. 합병 시너지로 연간 3,000~4,000억원 이상의 영업이익 플러스 효과가 기대된다.","key_points":["목표주가 34,000원에서 40,000원으로 상향, 아시아나항공 합병 기일 12월 16일 확정으로 2027년 본격 시너지 기대 및 연간 3,000~4,000억원 영업이익 플러스 효과 예상","2Q26 연결 기준 영업손실 1,648억원 예상(유류비 전년대비 87% 급증)이나, 3Q26 별도 기준 영업이익 4,649억원(+23.6% YoY) 호실적 전망 - 유가 하락과 유류할증료 스프레드 효과","중동 전쟁으로 중동 항공사 운항 편수 감소, 환승 수요 아시아 항공사로 이전되며 대한항공 미주·구주 노선 여객 수 증가 및 운임 상승 지속"],"is_new":false}],"consensus":{"Q":{"period":"2026년 2분기","latest":-184253846153.84998,"is_new":false,"series":[{"date":"2026-05-27","value":-244023076923.08},{"date":"2026-06-11","value":-230253846153.84998},{"date":"2026-06-12","value":-226946153846.15002},{"date":"2026-06-19","value":-190715384615.37997},{"date":"2026-06-23","value":-184253846153.84998}]},"Y":{"period":"2026년","latest":877542857142.8601,"is_new":false,"series":[{"date":"2026-05-27","value":740914285714.29},{"date":"2026-06-11","value":756057142857.1399},{"date":"2026-06-12","value":769271428571.4299},{"date":"2026-06-19","value":848700000000.0},{"date":"2026-06-23","value":877542857142.8601}]}},"briefing":{"briefing":"이번 하락은 아시아나항공과의 합병 인가 소식에도 불구하고 시장의 우려가 반영된 것으로 보입니다. 합병 과정에서의 불확실성과 관련된 규제 이슈가 투자 심리에 부정적인 영향을 미친 것으로 분석됩니다.","content_url":"http://www.yonhapnewstv.co.kr/news/MYH20260626054201QFT","article_title":"대한항공-아시아나 합병인가…12월 통합항공사 출범","change_rate":-3.61},"stk_flow":[{"date":"2026-06-26","외인":-8439036000,"개인":-3767484000,"기관":12635106000},{"date":"2026-06-25","외인":29977822000,"개인":-64382677000,"기관":36661795000},{"date":"2026-06-24","외인":8661634000,"개인":-20195325000,"기관":13267515000},{"date":"2026-06-23","외인":-4905649000,"개인":1554895000,"기관":4859834000},{"date":"2026-06-22","외인":9367644000,"개인":7290577000,"기관":-16972389000},{"date":"2026-06-19","외인":34626045000,"개인":-34114932000,"기관":-2565299000},{"date":"2026-06-18","외인":5608579000,"개인":-18831498000,"기관":12785542000}]},{"code":"020560","name":"아시아나항공","market":"KSP","price":7510.0,"change_pct":-2.59,"market_cap":1546990239610.0,"fwd_pe":null,"fwd_pb":null,"has_chart":true,"has_new":true,"news":[{"id":"1722004018202546478","title":"대한항공-아시아나항공 합병 인가…12월 17일 대한항공 통합","summary":"국토교통부는 대한항공이 자회사인 아시아나항공과 합병하고자 신청한 법인 합병 건과 관련해 ‘항공사업법’에 따른 엄격한 심사를 거쳐 합병을 인가했다고 밝혔다.\n\n대한항공은 이후 국토부 장관의 합병 인가를 신청했다.\n\n국토부는 관련 법령에 따른 심사 결과, 합병을 조건부 인가하기로 결정했다.","url":"https://zdnet.co.kr/view/?no=20260626143116","published_at":"2026-06-26T14:32:14","sentiment":"positive","is_new":true}],"disclosures":[{"date":"2026-06-26T07:49:28","title":"[기재정정]주요사항보고서(회사합병결정)","url":"https://dart.fss.or.kr/dsaf001/main.do?rcpNo=20260626000007","is_new":true}],"reports":[],"consensus":{"Q":{"period":"2026년 2분기","latest":-349000000000.0,"is_new":false,"series":[{"date":"2026-05-27","value":-349000000000.0}]},"Y":{"period":"2026년","latest":-570000000000.0,"is_new":false,"series":[{"date":"2026-05-27","value":-570000000000.0}]}},"briefing":{"briefing":"이번 하락은 대한항공과의 합병 인가 소식이 전해지면서 발생한 것으로 보입니다. 합병 과정에서의 불확실성과 경쟁력 저하 우려가 투자 심리에 부정적인 영향을 미친 것으로 분석됩니다.","content_url":"https://zdnet.co.kr/view/?no=20260626143116","article_title":"대한항공-아시아나항공 합병 인가…12월 17일 대한항공 통합","change_rate":-2.59},"stk_flow":[{"date":"2026-06-26","외인":-65793000,"개인":-80176000,"기관":199565000},{"date":"2026-06-25","외인":341470000,"개인":-1540464000,"기관":1212715000},{"date":"2026-06-24","외인":169348000,"개인":-491330000,"기관":338552000},{"date":"2026-06-23","외인":-376010000,"개인":172427000,"기관":225553000},{"date":"2026-06-22","외인":195010000,"개인":-232249000,"기관":410004000},{"date":"2026-06-19","외인":147355000,"개인":-321482000,"기관":124137000},{"date":"2026-06-18","외인":-610763000,"개인":-401570000,"기관":1038218000}]},{"code":"089590","name":"제주항공","market":"KSP","price":4540.0,"change_pct":-2.47,"market_cap":366110071900.0,"fwd_pe":5.5501223,"fwd_pb":null,"has_chart":true,"has_new":true,"news":[{"id":"1722018878202188028","title":"제주항공 ‘인천-제주’ 정기편 10월24일까지 운항","summary":"국토부, 사업계획 변경 인가 제주항공의 ‘인천-제주’ 정기편이 10월 24일까지 운항하게 됐다.\n\n국토교통부는 제주항공이 요청한 인천-제주 국내선 정기편을 올 하계시즌이 종료되는 10월 24일까지 계속 운항하기 위해 신청한 사업계획 변경을 인가했다고 26일 밝혔다.\n\n국토부는 인천-제주 노선이 수도권과 제주를 연결하는 기존 국내선 수요는 물론, 인천국제공항을 이용하는 해외관광객과 환승객 수요를 흡수하며 안정적으로 정착하고 있는 것으로 평가했다.","url":"https://biz.heraldcorp.com/article/10789650","published_at":"2026-06-26T15:30:00","sentiment":"positive","is_new":true},{"id":"1722676229297017492","title":"거점 공항 상업시설 입점률 늘어날 동안, 중소 공항은 줄었다…“패키지 입찰 필요”","summary":"한국공항공사가 운영하는 14개 공항 중 김포·김해·제주공항 등 거점 공항의 상업시설 입점률이 늘었지만 중소형 공항의 입점률은 줄어든 것으로 나타났다.\n\n반면 같은 기간 11개 중소형 공항(청주·대구·광주·울산·양양·여수·사천·포항·군산·원주·무안)의 상업시설 운영률은 96.61%에서 92%로 4.61%포인트 줄었다.\n\n중소형 공항의 상업시설 운영률이 떨어지는 이유는 이들 공항의 여객수요가 부족하기 때문이다.","url":"https://www.hani.co.kr/arti/area/capital/1265649.html","published_at":"2026-06-28T11:02:19","sentiment":"neutral","is_new":true}],"disclosures":[],"reports":[],"consensus":{"Q":{"period":"2026년 2분기","latest":-54042857142.86,"is_new":false,"series":[{"date":"2026-05-27","value":-55400000000.0},{"date":"2026-05-29","value":-59328571428.57},{"date":"2026-06-11","value":-54042857142.86}]},"Y":{"period":"2026년","latest":-4387500000.0,"is_new":false,"series":[{"date":"2026-05-27","value":-6500000000.0},{"date":"2026-05-29","value":-5887500000.0},{"date":"2026-06-11","value":-4387500000.0}]}},"briefing":{"briefing":"이 하락세는 특별한 외부 요인 없이 나타났지만, 최근 인천-제주 노선의 연장 운항 결정과 5개월 연속 월간 수송객 100만명 돌파 소식이 있었습니다. 이러한 긍정적인 이슈에도 불구하고 주가는 하락세를 보였으며, 이는 시장의 전반적인 분위기와 관련이 있을 수 있습니다.","content_url":"https://www.donga.com/news/Economy/article/all/20260619/134141684/1","article_title":"제주항공, 5개월 연속 월간 수송객 100만명 돌파","change_rate":-2.47},"stk_flow":[{"date":"2026-06-26","외인":1057000,"개인":-146791000,"기관":163354000},{"date":"2026-06-25","외인":44799000,"개인":119361000,"기관":-171033000},{"date":"2026-06-24","외인":37721000,"개인":8788000,"기관":-49756000},{"date":"2026-06-23","외인":-110606000,"개인":-39508000,"기관":142797000},{"date":"2026-06-22","외인":29970000,"개인":44989000,"기관":-65528000},{"date":"2026-06-19","외인":5366000,"개인":-29953000,"기관":8608000},{"date":"2026-06-18","외인":81554000,"개인":-92771000,"기관":-2584000}]}],"market_data":{"charts":[],"tables":[]}}