{"slug":"banks","wics_1st":"금융","wics_2nd":"은행","wics_3rd":"은행","trading_date":"2026-05-06","previous_trading_date":"2026-05-04","generated_at":"2026-05-07T08:49:26","ai_summary":["카카오뱅크, 대출 성장 둔화에 따른 비이자 수익 다각화 필요","금융지주 CEO 3연임 제한 논의 본격화에 따른 지배구조 리스크","우리금융 컨센서스 4.7% 하향 및 기업은행 정책 리스크 부각"],"news":[{"id":"ce8267e78b83","title":"성장 주춤 카카오뱅크, 대출 外 무기 필요[클릭 e종목]","summary":"9개 분기 동안 순이익 체급 변동X 대출 규제 해소 가능성 낮아 \"운용수익률 개선해야\"인터넷은행 카카오뱅크의 성장세가 주춤해졌다.\n\n수신과 대출 잔액 모두 전 분기 대비 2% 내외로 늘어나는 데 그쳤다.\n\n이익 성장을 견인했던 가계대출이 정부 규제 영향으로 분기 평균 1.6% 성장하는 데 그쳤다.","keyword":"카카오뱅크 대출 외 무기","url":"https://view.asiae.co.kr/article/2026050616462209616","source":"아시아경제","published_at":"2026-05-07 06:50:00","sentiment":"negative","source_type":"news","is_new":false},{"id":"d19ace300415","title":"'체리피킹' 저격당한 호실적 인터넷뱅크, 중저신용 대출 실적 보니","summary":"카카오뱅크의 올해 1분기 중·저신용 대출 신규 취급 비중은 45.6%, 잔액 기준 비중은 32.3%로 목표치를 상회했다.\n\n1분기 실적 발표를 앞둔 토스뱅크의 중저신용자 대출 비중은 지난해 말 기준 34.9%다.\n\n금융당국은 인터넷은행의 중저신용자 대출 목표를 더 높일 계획이다.","keyword":"인터넷은행 중저신용대출","url":"https://www.news1.kr/finance/general-finance/6158462","source":"뉴스1","published_at":"2026-05-07 06:20:00","sentiment":"neutral","source_type":"news","is_new":false},{"id":"40dcacc87c21","title":"금융지주 ‘3연임 제한’ 유력… “과한 개입” vs “폐쇄 구조 차단”","summary":"금융위, 지배구조 개선안 이달 발표‘총 6년 임기 제한’ 도입 가능성도 ‘고문 후 복귀’ 우회 연임도 막을 듯 “대기업은 두고 금융만 족쇄” 반발 조기 레임덕에 실적 약화 주장도 당국 “위기엔 공적자금… 규제 필요” 금융당국이 금융지주 회장의 ‘3연임 제한’을 금융회사 지배구조법에 명문화하는 방안을 유력 검토하고 있다.\n\n금융당국은 “금융회사는 위기 시 공적자금이 투입될 수 있는 만큼 일반 기업보다 강한 지배구조 규제가 필요하다”는 입장이다.\n\n또 금융회사는 위기 시 공적자금이 투입될 수 있는 만큼 일반 기업보다 강한 지배구조 규제","keyword":"금융지주 3연임 제한","url":"https://www.seoul.co.kr/news/economy/finance/2026/05/07/20260507029004","source":"서울신문","published_at":"2026-05-07 05:04:00","sentiment":"neutral","source_type":"news","is_new":false},{"id":"a8671cc8719f","title":"[이코노 브리핑] 카뱅, 1분기 순이익 1873억 역대 최대 외","summary":"하나銀, 달리기 기록과 연계 ‘적금’ 출시 하나은행이 달리기 기록에 따라 금리 혜택을 제공하는 ‘달려라 하나 적금’을 출시했다.\n\n이 적금은 고객의 달리기 기록에 따라 연 1.5~2.5%의 우대금리를 제공한다.\n\n국민카드, 간편결제 특화 카드 선보여 KB국민카드가 온·오프라인 간편결제 시 할인 혜택을 제공하는 ‘KB 니드 페이(NEED Pay) 카드’를 출시했다고 6일 밝혔다.","keyword":"하나은행 적금 출시","url":"https://www.segye.com/newsView/20260506514946","source":"세계","published_at":"2026-05-07 05:02:16","sentiment":"positive","source_type":"news","is_new":false},{"id":"e2cfda42106c","title":"KB가 로봇 만든 이유...‘시니어 돌봄’ 꽂힌 금융권","summary":"시니어 고객의 은퇴자산 관리 수요와 돌봄 수요를 겨냥해 금융권이 요양시설과 ‘돌봄 로봇’까지 접점을 넓히는 모습이다.\n\n고령층 고객은 은퇴자산 관리 수요뿐 아니라 건강, 안전, 돌봄, 주거 등 다양한 수요를 갖고 있기 때문이다.\n\n금융권 관계자는 “시니어 고객의 수요는 은퇴자산 관리에 그치지 않고 안전, 건강, 돌봄, 주거 영역까지 넓어지고 있다”며 “금융회사가 보유한 고객 기반과 계열사 역량을 활용해 생활밀착형 시니어 사업을 확대하려는 흐름”이라고 말했다.","keyword":"KB 시니어 돌봄 로봇","url":"https://www.sedaily.com/article/20040962","source":"서울경제","published_at":"2026-05-07 05:01:00","sentiment":"positive","source_type":"news","is_new":false}],"us_movers":[],"stocks":[{"code":"279570","name":"케이뱅크","price":6080.0,"change_pct":-3.34,"market_cap":2466626518080.0,"has_chart":true,"news":[],"disclosures":[{"date":"2026-04-30T17:28:09","title":"기업설명회(IR)개최(안내공시)              ","url":"https://dart.fss.or.kr/dsaf001/main.do?rcpNo=20260430801685","is_new":false},{"date":"2026-04-30T15:22:56","title":"영업(잠정)실적(공정공시)              ","url":"https://dart.fss.or.kr/dsaf001/main.do?rcpNo=20260430800869","is_new":false}],"reports":[],"consensus":{"Q":[],"Y":[]},"stk_flow":[{"date":"2026-05-06","외인":-6393218000,"개인":7128590000,"기관":-166851000},{"date":"2026-05-04","외인":1650950000,"개인":-1486276000,"기관":-78961000},{"date":"2026-04-30","외인":-70495000,"개인":-161214000,"기관":327497000},{"date":"2026-04-29","외인":-650855000,"개인":-629619000,"기관":1635511000},{"date":"2026-04-28","외인":-1561322000,"개인":1362012000,"기관":49008000},{"date":"2026-04-27","외인":-4578678000,"개인":5093184000,"기관":-262342000},{"date":"2026-04-24","외인":2502106000,"개인":-2074749000,"기관":-768473000}]},{"code":"175330","name":"JB금융지주","price":26550.0,"change_pct":-2.93,"market_cap":4998132655200.0,"has_chart":true,"news":[],"disclosures":[],"reports":[],"consensus":{"Q":[{"date":"2026-05-06","term":"Q","period":"2026년 2분기","value":284000000000.0,"previous":282363636363.64,"change_pct":0.58,"is_new":true},{"date":"2026-04-27","term":"Q","period":"2026년 2분기","value":282363636363.64,"previous":281700000000.0,"change_pct":0.24,"is_new":false},{"date":"2026-04-24","term":"Q","period":"2026년 2분기","value":281700000000.0,"previous":284428571428.56995,"change_pct":-0.96,"is_new":false},{"date":"2026-04-23","term":"Q","period":"2026년 2분기","value":284428571428.56995,"previous":284000000000.0,"change_pct":0.15,"is_new":false},{"date":"2026-04-10","term":"Q","period":"2026년 2분기","value":284000000000.0,"previous":null,"change_pct":null,"is_new":false}],"Y":[{"date":"2026-05-06","term":"Y","period":"2026년","value":1018707142857.1399,"previous":1019635714285.71,"change_pct":-0.09,"is_new":true},{"date":"2026-04-27","term":"Y","period":"2026년","value":1019635714285.71,"previous":1025564285714.29,"change_pct":-0.58,"is_new":false},{"date":"2026-04-24","term":"Y","period":"2026년","value":1025564285714.29,"previous":1036507692307.6901,"change_pct":-1.06,"is_new":false},{"date":"2026-04-23","term":"Y","period":"2026년","value":1036507692307.6901,"previous":1037892307692.3099,"change_pct":-0.13,"is_new":false},{"date":"2026-04-16","term":"Y","period":"2026년","value":1037892307692.3099,"previous":null,"change_pct":null,"is_new":false}]},"stk_flow":[{"date":"2026-05-06","외인":-1353615000,"개인":3692211000,"기관":-2615075000},{"date":"2026-05-04","외인":-1393627000,"개인":2283267000,"기관":-1206728000},{"date":"2026-04-30","외인":-3334990000,"개인":399502000,"기관":2926921000},{"date":"2026-04-29","외인":256950000,"개인":3634636000,"기관":-3927248000},{"date":"2026-04-28","외인":-1363056000,"개인":2817145000,"기관":-1469672000},{"date":"2026-04-27","외인":-3688230000,"개인":14010753000,"기관":-10528362000},{"date":"2026-04-24","외인":-4284006000,"개인":7341620000,"기관":-3071736000}]},{"code":"024110","name":"기업은행","price":21600.0,"change_pct":-2.26,"market_cap":17224398770400.0,"has_chart":true,"news":[{"id":"1703364494656409669","title":"[사설]금융기관 이전공약 봇물..경쟁력은 뒷전","summary":"우선 여야 대구광역시장 후보들인 김부겸 더불어민주당 후보와 추경호 국민의힘 후보가 IBK기업은행 대구 이전을 공약으로 내놨다.\n\n산업은행, 수출입은행 등도 이전 관련 공약이 나온다.\n\n부산 이전 공약이 나온 뒤 해당 연도 퇴사 인원이 이전보다 2 ~ 3배 늘어난 산업은행이 대표적인 경우다.","url":"https://www.mt.co.kr/opinion/2026/05/06/2026050200582294489","published_at":"2026-05-06T04:05:00","sentiment":"negative","is_new":true},{"id":"1703494460970766581","title":"이 대통령 \"금융기관은 돈 버는 게 능사? 그런 생각 자체가 문제\"","summary":"\"포용금융은 금융기관 의무 중 하나, 계속 주지시켜야\" 강조 ▲ 이재명 대통령이 6일 청와대에서 열린 국무회의 겸 비상경제점검회의에서 발언하고 있다.\n\n\" 이재명 대통령이 6일 국무회의에서 김용범 청와대 정책실장에게 힘을 실었다.\n\n이 대통령은 이날 \"정책실장께서 '금융기관은 준공공기관이다' 페이스북에 글을 써서, 아주 잘 지적하셨던 것 같다.","url":"https://www.ohmynews.com/NWS_Web/View/at_pg.aspx?CNTN_CD=A0003231509&CMPT_CD=P0010&utm_medium=newsearch","published_at":"2026-05-06T12:41:00","sentiment":"negative","is_new":true}],"disclosures":[],"reports":[],"consensus":{"Q":[{"date":"2026-05-06","term":"Q","period":"2026년 2분기","value":965500000000.0,"previous":971111111111.11,"change_pct":-0.58,"is_new":true},{"date":"2026-05-04","term":"Q","period":"2026년 2분기","value":971111111111.11,"previous":967500000000.0,"change_pct":0.37,"is_new":false},{"date":"2026-04-27","term":"Q","period":"2026년 2분기","value":967500000000.0,"previous":973333333333.3301,"change_pct":-0.6,"is_new":false},{"date":"2026-04-24","term":"Q","period":"2026년 2분기","value":973333333333.3301,"previous":979166666666.6699,"change_pct":-0.6,"is_new":false},{"date":"2026-04-15","term":"Q","period":"2026년 2분기","value":979166666666.6699,"previous":null,"change_pct":null,"is_new":false}],"Y":[{"date":"2026-05-06","term":"Y","period":"2026년","value":3728816666666.67,"previous":3745128571428.57,"change_pct":-0.44,"is_new":true},{"date":"2026-05-04","term":"Y","period":"2026년","value":3745128571428.57,"previous":3743907692307.69,"change_pct":0.03,"is_new":false},{"date":"2026-04-27","term":"Y","period":"2026년","value":3743907692307.69,"previous":3786275000000.0,"change_pct":-1.12,"is_new":false},{"date":"2026-04-24","term":"Y","period":"2026년","value":3786275000000.0,"previous":3782869230769.23,"change_pct":0.09,"is_new":false},{"date":"2026-04-20","term":"Y","period":"2026년","value":3782869230769.23,"previous":null,"change_pct":null,"is_new":false}]},"stk_flow":[{"date":"2026-05-06","외인":5160657000,"개인":19537324000,"기관":-24851009000},{"date":"2026-05-04","외인":-16221568000,"개인":20564737000,"기관":-5330515000},{"date":"2026-04-30","외인":-4463826000,"개인":-5918085000,"기관":7942715000},{"date":"2026-04-29","외인":1499251000,"개인":-2183275000,"기관":-1036190000},{"date":"2026-04-28","외인":10496573000,"개인":-11991715000,"기관":1778827000},{"date":"2026-04-27","외인":-2847741000,"개인":3701724000,"기관":-904406000},{"date":"2026-04-24","외인":4110862000,"개인":-3075193000,"기관":-684383000}]},{"code":"316140","name":"우리금융지주","price":32600.0,"change_pct":-2.1,"market_cap":23930888032000.0,"has_chart":true,"news":[],"disclosures":[{"date":"2026-05-06T07:31:24","title":"효력발생안내( 2026.4.24. 제출 일괄신고서 )","url":"https://dart.fss.or.kr/dsaf001/main.do?rcpNo=20260424100005","is_new":true},{"date":"2026-04-29T16:20:37","title":"[기재정정]주요사항보고서(주식교환ㆍ이전결정)","url":"https://dart.fss.or.kr/dsaf001/main.do?rcpNo=20260429000768","is_new":false},{"date":"2026-04-29T16:05:35","title":"기업설명회(IR)개최(안내공시)              ","url":"https://dart.fss.or.kr/dsaf001/main.do?rcpNo=20260429800718","is_new":false}],"reports":[{"broker":"대신증권","title":"26년 배당수익률 1등","url":"https://ddi-cdn.deepsearch.com/research/company/2026/04/29/1700917370102616083/000-a41fa6dfb4a0b792b405c9c39cce2f3a7386d24e.pdf","date":"2026-04-29T10:02:10","summary":"대신증권은 우리금융지주(316140)에 대해 투자의견 매수(BUY)와 목표주가 43,000원을 유지했다. 1Q26 실적은 거액 충당금과 판관비 증가로 컨센서스를 하회했으나, CET1비율이 전분기 대비 70bp 상승한 13.6%를 기록하며 자본안정성을 입증했다. 유형자산재평가로 1.8조원 이익이 반영된 영향이 크다. 우리투자증권 증자 1조원, 동양생명 완전자회사화 등 비은행 계열사 강화가 진행 중이며, 2026년 DPS 1,510원(YoY +11%), 비과세 배당 감안 시 실질 배당금 증가율 19.1%로 커버리지 금융지주 중 최고 배당수익률이 기대된다.","key_points":["1Q26 CET1비율 13.6% 달성(전분기 대비 +70bp): 유형자산재평가로 세후 1.8조원 이익 반영, 커버리지 금융지주 중 두 번째로 높은 자본안정성 확보","2026년 DPS 1,510원(YoY +11%) 전망, 비과세 배당 효과 감안 시 실질 증가율 19.1%로 커버리지 금융지주 중 최고 배당수익률(4.5%) 예상","우리투자증권 증자 1조원 및 동양생명 완전자회사화 공시로 비은행 계열사 강화 가속화, CET1비율 영향 없이 진행되며 총환원율 50%까지 상승 가능"],"is_new":false}],"consensus":{"Q":[{"date":"2026-05-06","term":"Q","period":"2026년 2분기","value":1307500000000.0,"previous":1281125000000.0,"change_pct":2.06,"is_new":true},{"date":"2026-04-24","term":"Q","period":"2026년 2분기","value":1281125000000.0,"previous":1281375000000.0,"change_pct":-0.02,"is_new":false},{"date":"2026-04-15","term":"Q","period":"2026년 2분기","value":1281375000000.0,"previous":1284428571428.57,"change_pct":-0.24,"is_new":false},{"date":"2026-04-07","term":"Q","period":"2026년 2분기","value":1284428571428.57,"previous":1275285714285.7102,"change_pct":0.72,"is_new":false},{"date":"2026-04-02","term":"Q","period":"2026년 2분기","value":1275285714285.7102,"previous":null,"change_pct":null,"is_new":false}],"Y":[{"date":"2026-05-06","term":"Y","period":"2026년","value":4346433333333.33,"previous":4561868750000.0,"change_pct":-4.72,"is_new":true},{"date":"2026-04-24","term":"Y","period":"2026년","value":4561868750000.0,"previous":4555618750000.0,"change_pct":0.14,"is_new":false},{"date":"2026-04-16","term":"Y","period":"2026년","value":4555618750000.0,"previous":4563431250000.0,"change_pct":-0.17,"is_new":false},{"date":"2026-04-15","term":"Y","period":"2026년","value":4563431250000.0,"previous":4565306250000.0,"change_pct":-0.04,"is_new":false},{"date":"2026-04-07","term":"Y","period":"2026년","value":4565306250000.0,"previous":null,"change_pct":null,"is_new":false}]},"stk_flow":[{"date":"2026-05-06","외인":-30419452000,"개인":18455758000,"기관":-28028055000},{"date":"2026-05-04","외인":-22767035000,"개인":4892863000,"기관":-1009894000},{"date":"2026-04-30","외인":-23884609000,"개인":-7513468000,"기관":17226295000},{"date":"2026-04-29","외인":-7840054000,"개인":-306602000,"기관":-5318163000},{"date":"2026-04-28","외인":-9268815000,"개인":-9573896000,"기관":7890169000},{"date":"2026-04-27","외인":-107133316000,"개인":108637078000,"기관":-34687077000},{"date":"2026-04-24","외인":-7349594000,"개인":2194852000,"기관":5061108000}]},{"code":"139130","name":"iM금융지주","price":18980.0,"change_pct":-1.66,"market_cap":3048654585340.0,"has_chart":true,"news":[],"disclosures":[],"reports":[],"consensus":{"Q":[{"date":"2026-05-06","term":"Q","period":"2026년 2분기","value":216636363636.36,"previous":211571428571.43,"change_pct":2.39,"is_new":true},{"date":"2026-04-28","term":"Q","period":"2026년 2분기","value":211571428571.43,"previous":214666666666.66998,"change_pct":-1.44,"is_new":false},{"date":"2026-04-14","term":"Q","period":"2026년 2분기","value":214666666666.66998,"previous":214500000000.0,"change_pct":0.08,"is_new":false},{"date":"2026-04-09","term":"Q","period":"2026년 2분기","value":214500000000.0,"previous":212000000000.0,"change_pct":1.18,"is_new":false},{"date":"2026-04-07","term":"Q","period":"2026년 2분기","value":212000000000.0,"previous":null,"change_pct":null,"is_new":false}],"Y":[{"date":"2026-05-06","term":"Y","period":"2026년","value":671371428571.4299,"previous":687883333333.3301,"change_pct":-2.4,"is_new":true},{"date":"2026-04-28","term":"Y","period":"2026년","value":687883333333.3301,"previous":684883333333.3301,"change_pct":0.44,"is_new":false},{"date":"2026-04-16","term":"Y","period":"2026년","value":684883333333.3301,"previous":687145454545.45,"change_pct":-0.33,"is_new":false},{"date":"2026-04-14","term":"Y","period":"2026년","value":687145454545.45,"previous":681716666666.6699,"change_pct":0.8,"is_new":false},{"date":"2026-04-10","term":"Y","period":"2026년","value":681716666666.6699,"previous":null,"change_pct":null,"is_new":false}]},"stk_flow":[{"date":"2026-05-06","외인":5352226000,"개인":-808242000,"기관":-4538298000},{"date":"2026-05-04","외인":5581478000,"개인":-4959863000,"기관":-306649000},{"date":"2026-04-30","외인":7179285000,"개인":-6281649000,"기관":-789521000},{"date":"2026-04-29","외인":1128084000,"개인":557223000,"기관":-1745209000},{"date":"2026-04-28","외인":2444269000,"개인":-1911694000,"기관":-433584000},{"date":"2026-04-27","외인":-459425000,"개인":-1077023000,"기관":839399000},{"date":"2026-04-24","외인":-1321587000,"개인":718698000,"기관":597267000}]},{"code":"086790","name":"하나금융지주","price":125500.0,"change_pct":-0.87,"market_cap":34433152374000.0,"has_chart":true,"news":[],"disclosures":[{"date":"2026-05-06T15:52:13","title":"임원ㆍ주요주주특정증권등소유상황보고서","url":"https://dart.fss.or.kr/dsaf001/main.do?rcpNo=20260506000466","is_new":true},{"date":"2026-04-30T16:48:04","title":"증권발행실적보고서","url":"https://dart.fss.or.kr/dsaf001/main.do?rcpNo=20260430001646","is_new":false},{"date":"2026-04-29T17:35:40","title":"투자설명서(일괄신고)","url":"https://dart.fss.or.kr/dsaf001/main.do?rcpNo=20260429001095","is_new":false},{"date":"2026-04-29T17:30:40","title":"일괄신고추가서류","url":"https://dart.fss.or.kr/dsaf001/main.do?rcpNo=20260429001079","is_new":false}],"reports":[],"consensus":{"Q":[{"date":"2026-05-06","term":"Q","period":"2026년 2분기","value":1638466666666.6702,"previous":1574000000000.0,"change_pct":4.1,"is_new":true},{"date":"2026-04-24","term":"Q","period":"2026년 2분기","value":1574000000000.0,"previous":1567142857142.8599,"change_pct":0.44,"is_new":false},{"date":"2026-04-15","term":"Q","period":"2026년 2분기","value":1567142857142.8599,"previous":1563166666666.6702,"change_pct":0.25,"is_new":false},{"date":"2026-04-07","term":"Q","period":"2026년 2분기","value":1563166666666.6702,"previous":1554666666666.6702,"change_pct":0.55,"is_new":false},{"date":"2026-04-02","term":"Q","period":"2026년 2분기","value":1554666666666.6702,"previous":null,"change_pct":null,"is_new":false}],"Y":[{"date":"2026-05-06","term":"Y","period":"2026년","value":5984985000000.0,"previous":5801226666666.67,"change_pct":3.17,"is_new":true},{"date":"2026-04-24","term":"Y","period":"2026년","value":5801226666666.67,"previous":5797626666666.67,"change_pct":0.06,"is_new":false},{"date":"2026-04-16","term":"Y","period":"2026년","value":5797626666666.67,"previous":5798893333333.33,"change_pct":-0.02,"is_new":false},{"date":"2026-04-15","term":"Y","period":"2026년","value":5798893333333.33,"previous":5785360000000.0,"change_pct":0.23,"is_new":false},{"date":"2026-04-07","term":"Y","period":"2026년","value":5785360000000.0,"previous":null,"change_pct":null,"is_new":false}]},"stk_flow":[{"date":"2026-05-06","외인":30150420000,"개인":2307091000,"기관":-32644817000},{"date":"2026-05-04","외인":-5230416000,"개인":8065083000,"기관":-3085142000},{"date":"2026-04-30","외인":-6892427000,"개인":-4783839000,"기관":11086500000},{"date":"2026-04-29","외인":28864347000,"개인":-10840115000,"기관":-17785694000},{"date":"2026-04-28","외인":29134518000,"개인":-22522777000,"기관":-6834620000},{"date":"2026-04-27","외인":18459651000,"개인":-4837024000,"기관":-13519187000},{"date":"2026-04-24","외인":14417137000,"개인":-17685489000,"기관":3510414000}]},{"code":"055550","name":"신한지주","price":97300.0,"change_pct":-0.71,"market_cap":46183869325300.0,"has_chart":true,"news":[],"disclosures":[],"reports":[],"consensus":{"Q":[{"date":"2026-05-06","term":"Q","period":"2026년 2분기","value":2197153846153.85,"previous":2125666666666.6702,"change_pct":3.36,"is_new":true},{"date":"2026-04-23","term":"Q","period":"2026년 2분기","value":2125666666666.6702,"previous":2130666666666.6702,"change_pct":-0.23,"is_new":false},{"date":"2026-04-15","term":"Q","period":"2026년 2분기","value":2130666666666.6702,"previous":2123875000000.0,"change_pct":0.32,"is_new":false},{"date":"2026-04-07","term":"Q","period":"2026년 2분기","value":2123875000000.0,"previous":2126428571428.57,"change_pct":-0.12,"is_new":false},{"date":"2026-04-03","term":"Q","period":"2026년 2분기","value":2126428571428.57,"previous":null,"change_pct":null,"is_new":false}],"Y":[{"date":"2026-05-06","term":"Y","period":"2026년","value":7597400000000.0,"previous":7575847058823.53,"change_pct":0.28,"is_new":true},{"date":"2026-05-04","term":"Y","period":"2026년","value":7575847058823.53,"previous":7549317647058.819,"change_pct":0.35,"is_new":false},{"date":"2026-04-24","term":"Y","period":"2026년","value":7549317647058.819,"previous":7500133333333.33,"change_pct":0.66,"is_new":false},{"date":"2026-04-23","term":"Y","period":"2026년","value":7500133333333.33,"previous":7497533333333.33,"change_pct":0.03,"is_new":false},{"date":"2026-04-16","term":"Y","period":"2026년","value":7497533333333.33,"previous":null,"change_pct":null,"is_new":false}]},"stk_flow":[{"date":"2026-05-06","외인":24591990000,"개인":499644000,"기관":-24794707000},{"date":"2026-05-04","외인":-22799786000,"개인":30003108000,"기관":-7443822000},{"date":"2026-04-30","외인":-7484177000,"개인":-12891016000,"기관":20594795000},{"date":"2026-04-29","외인":16040450000,"개인":-702189000,"기관":-15391719000},{"date":"2026-04-28","외인":454150000,"개인":-1738593000,"기관":1287635000},{"date":"2026-04-27","외인":-2125635000,"개인":5074443000,"기관":-3006726000},{"date":"2026-04-24","외인":-7719705000,"개인":-6036538000,"기관":14955886000}]},{"code":"105560","name":"KB금융","price":158900.0,"change_pct":0.7,"market_cap":59245937299500.0,"has_chart":true,"news":[],"disclosures":[{"date":"2026-05-04T16:12:22","title":"임원ㆍ주요주주특정증권등소유상황보고서","url":"https://dart.fss.or.kr/dsaf001/main.do?rcpNo=20260504000344","is_new":false},{"date":"2026-04-30T17:18:07","title":"증권신고서(채무증권)","url":"https://dart.fss.or.kr/dsaf001/main.do?rcpNo=20260430001806","is_new":false},{"date":"2026-04-29T17:40:41","title":"해외증권거래소등에신고한사업보고서등의국내신고              ","url":"https://dart.fss.or.kr/dsaf001/main.do?rcpNo=20260429801135","is_new":false}],"reports":[],"consensus":{"Q":[{"date":"2026-05-06","term":"Q","period":"2026년 2분기","value":2402666666666.67,"previous":2391583333333.33,"change_pct":0.46,"is_new":true},{"date":"2026-04-27","term":"Q","period":"2026년 2분기","value":2391583333333.33,"previous":2340750000000.0,"change_pct":2.17,"is_new":false},{"date":"2026-04-23","term":"Q","period":"2026년 2분기","value":2340750000000.0,"previous":2342250000000.0,"change_pct":-0.06,"is_new":false},{"date":"2026-04-15","term":"Q","period":"2026년 2분기","value":2342250000000.0,"previous":2323571428571.43,"change_pct":0.8,"is_new":false},{"date":"2026-04-07","term":"Q","period":"2026년 2분기","value":2323571428571.43,"previous":null,"change_pct":null,"is_new":false}],"Y":[{"date":"2026-05-06","term":"Y","period":"2026년","value":9039841176470.59,"previous":9016135294117.648,"change_pct":0.26,"is_new":true},{"date":"2026-04-27","term":"Y","period":"2026년","value":9016135294117.648,"previous":8958194117647.06,"change_pct":0.65,"is_new":false},{"date":"2026-04-24","term":"Y","period":"2026년","value":8958194117647.06,"previous":8750873333333.33,"change_pct":2.37,"is_new":false},{"date":"2026-04-23","term":"Y","period":"2026년","value":8750873333333.33,"previous":8739606666666.67,"change_pct":0.13,"is_new":false},{"date":"2026-04-16","term":"Y","period":"2026년","value":8739606666666.67,"previous":null,"change_pct":null,"is_new":false}]},"stk_flow":[{"date":"2026-05-06","외인":67425835000,"개인":-31517434000,"기관":-35932608000},{"date":"2026-05-04","외인":-31203371000,"개인":48705945000,"기관":-17909598000},{"date":"2026-04-30","외인":14996976000,"개인":-21923629000,"기관":7421894000},{"date":"2026-04-29","외인":27217760000,"개인":-20453946000,"기관":-5932225000},{"date":"2026-04-28","외인":21360112000,"개인":-24338004000,"기관":3286309000},{"date":"2026-04-27","외인":-9472204000,"개인":14256122000,"기관":-5162809000},{"date":"2026-04-24","외인":-48043547000,"개인":15015438000,"기관":31673690000}]},{"code":"138930","name":"BNK금융지주","price":18130.0,"change_pct":-0.38,"market_cap":5626229108290.0,"has_chart":true,"news":[],"disclosures":[{"date":"2026-05-04T17:27:29","title":"기업설명회(IR)개최(안내공시)              ","url":"https://dart.fss.or.kr/dsaf001/main.do?rcpNo=20260504800774","is_new":false},{"date":"2026-04-30T14:52:53","title":"주식소각결정              ","url":"https://dart.fss.or.kr/dsaf001/main.do?rcpNo=20260430800736","is_new":false},{"date":"2026-04-30T14:42:52","title":"주요사항보고서(자기주식취득신탁계약체결결정)","url":"https://dart.fss.or.kr/dsaf001/main.do?rcpNo=20260430000910","is_new":false},{"date":"2026-04-30T14:17:51","title":"현금ㆍ현물배당결정              ","url":"https://dart.fss.or.kr/dsaf001/main.do?rcpNo=20260430800627","is_new":false},{"date":"2026-04-30T14:17:51","title":"연결재무제표기준영업(잠정)실적(공정공시)              ","url":"https://dart.fss.or.kr/dsaf001/main.do?rcpNo=20260430800567","is_new":false},{"date":"2026-04-30T12:17:40","title":"현금ㆍ현물배당을위한주주명부폐쇄(기준일)결정              ","url":"https://dart.fss.or.kr/dsaf001/main.do?rcpNo=20260430800401","is_new":false},{"date":"2026-04-30T11:22:38","title":"연결재무제표기준영업(잠정)실적(공정공시)(자회사의 주요경영사항)              ","url":"https://dart.fss.or.kr/dsaf001/main.do?rcpNo=20260430800335","is_new":false}],"reports":[],"consensus":{"Q":[{"date":"2026-05-06","term":"Q","period":"2026년 2분기","value":334750000000.0,"previous":319857142857.14,"change_pct":4.66,"is_new":true},{"date":"2026-04-30","term":"Q","period":"2026년 2분기","value":319857142857.14,"previous":315833333333.32996,"change_pct":1.27,"is_new":false},{"date":"2026-04-16","term":"Q","period":"2026년 2분기","value":315833333333.32996,"previous":314333333333.32996,"change_pct":0.48,"is_new":false},{"date":"2026-04-10","term":"Q","period":"2026년 2분기","value":314333333333.32996,"previous":306600000000.0,"change_pct":2.52,"is_new":false},{"date":"2026-04-07","term":"Q","period":"2026년 2분기","value":306600000000.0,"previous":null,"change_pct":null,"is_new":false}],"Y":[{"date":"2026-05-06","term":"Y","period":"2026년","value":1117360000000.0,"previous":1111823076923.08,"change_pct":0.5,"is_new":true},{"date":"2026-04-30","term":"Y","period":"2026년","value":1111823076923.08,"previous":1118058333333.3298,"change_pct":-0.56,"is_new":false},{"date":"2026-04-16","term":"Y","period":"2026년","value":1118058333333.3298,"previous":1123141666666.6702,"change_pct":-0.45,"is_new":false},{"date":"2026-04-10","term":"Y","period":"2026년","value":1123141666666.6702,"previous":1128975000000.0,"change_pct":-0.52,"is_new":false},{"date":"2026-04-07","term":"Y","period":"2026년","value":1128975000000.0,"previous":null,"change_pct":null,"is_new":false}]},"stk_flow":[{"date":"2026-05-06","외인":3858433000,"개인":1253515000,"기관":-4958897000},{"date":"2026-05-04","외인":-10512632000,"개인":10705736000,"기관":-2971584000},{"date":"2026-04-30","외인":-5487223000,"개인":1856911000,"기관":357784000},{"date":"2026-04-29","외인":-2517128000,"개인":413752000,"기관":-1112948000},{"date":"2026-04-28","외인":-744667000,"개인":-1175831000,"기관":1917985000},{"date":"2026-04-27","외인":-4604779000,"개인":1870189000,"기관":2751102000},{"date":"2026-04-24","외인":-1553562000,"개인":-1243914000,"기관":2796224000}]}]}