{"slug":"display-equipment","wics_1st":"IT","wics_2nd":"디스플레이","wics_3rd":"디스플레이 장비 및 부품","trading_date":"2026-06-01","previous_trading_date":"2026-05-29","display_date":"2026-06-02","generated_at":"2026-06-02T07:09:17","sector_return":2.66,"ai_summary":["서울반도체, 글로벌 완성차 업체에 광반도체 공급","SDT-비바, QRNG 기반 AI CCTV 개발 착수","LX세미콘, 2년 연속 영업익 감소세 지속"],"news":[{"id":"7508f30d48a6","title":"글로벌 톱4 완성차 업체에 광반도체 칩 공급한 서울반도체","summary":"세계 최초 개발한 HV광반도체 기술 첫 양산 돌입 \"부품 수 줄이고 전력 소모량도 낮출 수 있어\"글로벌 광반도체 전문 기술 기업 서울반도체가 세계 최초로 개발한 ‘HV(High Voltage)광반도체’ 기술이 미국·유럽·아시아 글로벌 Top 자동차 4개 업체에서 양산을 시작, 연내 10개 모델로 확대될 예정이라고 1일 밝혔다.\n\n서울반도체의 ‘HV광반도체’ 기술은 별도 부품을 최소화해 PCB 설계를 단순화하고, 부품 수 줄일 수 있을 뿐만 아니라, 발열을 줄이고 내구성을 높였다.\n\n기존 3V LED 대비 드라이버 비용을 20% 줄이고 전력 소비도 10% 낮출 수 있다.","keyword":"광반도체공급","url":"https://www.hankyung.com/article/202606011291i","source":"한국경제","published_at":"2026-06-01 16:48:00","sentiment":"positive","source_type":"news","is_new":true},{"id":"763ec77b496b","title":"SDT-비바, 연 20만대 목표 QRNG 기반 AI CCTV 개발 나선다","summary":"양자기술 전문기업 SDT(대표 윤지원)와 영상보안 전문기업 비바(대표 임재학)는 ‘QRNG(양자난수생성) 암호화 AI CCTV 공동개발 및 양산 협력’을 위한 업무협약(MOU)을 체결했다고 1일 밝혔다.\n\n이에 SDT QRNG 보안 모듈과 비바 AI CCTV 하드웨어·소프트웨어를 통합해 CCTV 생산 전 구간에서 보안성이 한층 강화된 완제품으로 시장을 공략에 함께 나서겠다는 것.\n\n임재학 비바 대표는 \"AI CCTV가 공공·산업 현장으로 확대될수록 영상 데이터 신뢰성과 보안성은 제품 경쟁력의 핵심이 되고 있다\"며 \"비바의 영상보안 기술과 제조 역량에 SDT의 QRNG 양자보안 기술을 결합, 보안성이 검증된 차세대 AI CCTV 제품을 시장에 선보일 것\"이라고 말했다.","keyword":"양자보안CCTV","url":"https://zdnet.co.kr/view/?no=20260601170047","source":"지디넷코리아","published_at":"2026-06-01 17:01:00","sentiment":"positive","source_type":"news","is_new":true},{"id":"f9f67d2eff7c","title":"아이엘, 산업 자율주행로봇 'L1 맥스' 출시…피지컬AI 사업 확대","summary":"평지 시속 28km·계단 보행 하이브리드…데이터센터·발전소 자율순찰 겨냥 아이엘이 산업 현장용 자율주행 로봇을 선보이며 피지컬AI 기반 사업 확대에 나섰다.\n\n1일 아이엘은 4족 보행 로봇 '아이엘봇 L1 맥스'를 출시했다고 밝혔다.\n\n아이엘은 기존 휴머노이드 로봇 '아이엘봇 C2'와의 연계를 통해 이동·점검·작업 수행을 통합하는 운영 구조도 구축할 방침이다.","keyword":"자율주행로봇","url":"https://www.imaeil.com/page/view/2026060116184916613","source":"매일신문","published_at":"2026-06-01 16:26:00","sentiment":"positive","source_type":"news","is_new":true}],"global_research":[],"us_movers":[],"us_earnings":[],"stocks":[{"code":"108320","name":"LX세미콘","market":"KSP","price":55400.0,"change_pct":5.32,"market_cap":901042220000.0,"fwd_pe":8.869921,"fwd_pb":null,"has_chart":true,"has_new":true,"news":[{"id":"1712958029277827635","title":"\"반도체 기업인데\" LX세미콘, 영업익 2년째 감소세…실적 부진 언제까지","summary":"AI 반도체 호황에도 성장 흐름 소외 DDI 점유율 하락에 수익성 급악화 주가 최고점 대비 3분의 1 수준 추락 배당 부담 속 신사업 성과 미지수 [서울=뉴시스]유희석 기자 = 메모리칩 위주의 반도체 산업 초호황 속에서도 LX그룹 반도체 계열사 LX세미콘은 실적 둔화가 지속되고 있다.\n\n1일 업계에 따르면 LX세미콘의 지난해 연결 기준 영업이익은 1089억원으로 전년 1671억원 대비 34.8% 감소했다.\n\n업계 관계자는 \"LX세미콘은 디스플레이 업황 변동에 실적이 크게 좌우되는 사업 구조를 갖고 있다\"며 \"본업 경쟁력 회복과 함께 신사업 육성을 통한 수익원 다변화가 향후 실적 반등의 핵심이 될 것\"이라고 말했다.","url":"https://www.newsis.com/view/NISX20260601_0003651493","published_at":"2026-06-01T15:24:00","sentiment":"negative","is_new":true}],"disclosures":[{"date":"2026-06-01T13:54:13","title":"기업지배구조보고서공시              ","url":"https://dart.fss.or.kr/dsaf001/main.do?rcpNo=20260601800621","is_new":true},{"date":"2026-05-29T16:17:15","title":"대규모기업집단현황공시[연1회공시및1/4분기용(개별회사)]","url":"https://dart.fss.or.kr/dsaf001/main.do?rcpNo=20260529001776","is_new":false}],"reports":[],"consensus":{"Q":{"period":"2026년 2분기","latest":22000000000.0,"is_new":false,"series":[{"date":"2026-05-04","value":22000000000.0}]},"Y":{"period":"2026년","latest":100000000000.0,"is_new":false,"series":[{"date":"2026-05-04","value":100000000000.0}]}},"briefing":{"briefing":"이 상승은 반도체 산업의 전반적인 호황에도 불구하고 실적 부진이 지속되고 있는 가운데, 향후 신사업 성과에 대한 기대감이 반영된 것으로 보입니다. 특히, 본업 경쟁력 회복과 수익원 다변화가 실적 반등의 핵심으로 언급되고 있어 긍정적인 전망이 주가에 영향을 미친 것으로 분석됩니다.","content_url":"https://www.newsis.com/view/NISX20260601_0003651493","article_title":"\"반도체 기업인데\" LX세미콘, 영업익 2년째 감소세…실적 부진 언제까지","change_rate":5.32},"stk_flow":[{"date":"2026-06-01","외인":441193000,"개인":1439905000,"기관":-1931251000},{"date":"2026-05-29","외인":-786855000,"개인":3016845000,"기관":-2377575000},{"date":"2026-05-28","외인":-1262854000,"개인":2947774000,"기관":-1984009000},{"date":"2026-05-27","외인":-946726000,"개인":3338641000,"기관":-2408353000},{"date":"2026-05-26","외인":-639788000,"개인":647170000,"기관":72100000},{"date":"2026-05-22","외인":8977713000,"개인":-8947477000,"기관":-180435000},{"date":"2026-05-21","외인":-90057000,"개인":-467494000,"기관":652755000}]},{"code":"083500","name":"에프엔에스테크","market":"KSQ","price":19200.0,"change_pct":0.0,"market_cap":164653862400.0,"fwd_pe":null,"fwd_pb":null,"has_chart":true,"has_new":false,"news":[],"disclosures":[],"reports":[],"consensus":{"Q":{"period":"2026년 2분기","latest":4250000000.0,"is_new":false,"series":[{"date":"2026-05-04","value":4000000000.0},{"date":"2026-05-14","value":4250000000.0}]},"Y":{"period":"2026년","latest":18375000000.0,"is_new":false,"series":[{"date":"2026-05-04","value":18633333333.33},{"date":"2026-05-14","value":18733333333.33},{"date":"2026-05-19","value":18375000000.0}]}},"briefing":{"briefing":"주가가 크게 변동하지 않았지만, 최근 국민성장펀드와 관련된 정부의 투자 매력 증대 방안이 보도되었습니다. 이러한 이슈는 시장 전반에 영향을 미칠 수 있으나, 에프엔에스테크와의 직접적인 연관성은 확인되지 않았습니다.","content_url":"https://www.mk.co.kr/article/12055423","article_title":"역대 관제펀드에 울었는데…국민성장펀드, 이번엔 다를까 [스페셜리포트]","change_rate":0.0},"stk_flow":[{"date":"2026-06-01","외인":-164444000,"개인":-546201000,"기관":861717000},{"date":"2026-05-29","외인":-1893753000,"개인":622027000,"기관":1329556000},{"date":"2026-05-28","외인":729794000,"개인":-628607000,"기관":-244513000},{"date":"2026-05-27","외인":-85633000,"개인":-58144000,"기관":55259000},{"date":"2026-05-26","외인":-939040000,"개인":839293000,"기관":-11618000},{"date":"2026-05-22","외인":-1524505000,"개인":1830601000,"기관":-17817000},{"date":"2026-05-21","외인":-531017000,"개인":188488000,"기관":283136000}]}],"market_data":{"charts":[{"title":"Glass","unit":"CNY/t","last_date":"2026-06-01","last_val":1055.0,"prev_val":1049.0,"chg":6.0,"chg_pct":0.57,"series":[{"d":"2026-04-28","v":1051.0},{"d":"2026-04-29","v":1039.0},{"d":"2026-05-06","v":1065.0},{"d":"2026-05-07","v":1071.0},{"d":"2026-05-08","v":1065.0},{"d":"2026-05-11","v":1065.0},{"d":"2026-05-12","v":1061.0},{"d":"2026-05-13","v":1064.0},{"d":"2026-05-14","v":1053.0},{"d":"2026-05-15","v":1046.0},{"d":"2026-05-18","v":1036.0},{"d":"2026-05-19","v":1027.0},{"d":"2026-05-20","v":1017.0},{"d":"2026-05-21","v":1028.0},{"d":"2026-05-22","v":1023.0},{"d":"2026-05-25","v":1037.0},{"d":"2026-05-26","v":1026.0},{"d":"2026-05-27","v":1033.0},{"d":"2026-05-28","v":1038.0},{"d":"2026-05-29","v":1049.0},{"d":"2026-06-01","v":1055.0}]}],"tables":[]}}