{"slug":"food-products","wics_1st":"필수소비재","wics_2nd":"식품,음료,담배","wics_3rd":"식품","trading_date":"2026-05-22","previous_trading_date":"2026-05-21","display_date":"2026-05-26","generated_at":"2026-05-26T08:26:39","sector_return":1.56,"ai_summary":["CJ제일제당 등 K푸드 중국 반입 불허 명단 포함, 수출 리스크 점검 필요","농심 구미산단 입주 타진 및 글로벌 박람회 참가로 해외 확장 가속화","식품업계 B2B 시장 공략 강화 및 신성장 동력 확보 경쟁 심화"],"news":[{"id":"16b8b52f9e33","title":"잘 나가는 풀무원…강남 아파트 급식 첫 수주","summary":"래미안 블레스티지에 식음서비스 제공 단체 급식업계가 기업과 학교를 넘어 아파트 시장으로 사업 영역을 넓히는 가운데 풀무원푸드앤컬처가 서울 강남권 대단지 아파트 식음 서비스 시장에 처음 진출한다.\n\n기업 구내식당이 성장에 정체를 맞으면서 신규 시장으로 분류되는 아파트 식음 서비스를 둘러싼 업계 경쟁이 한층 치열해지는 모양새다.\n\n25일 업계에 따르면 풀무원푸드앤컬처는 서울 강남구 개포동 ‘래미안 블레스티지’의 식음 서비스를 수주하며 강남권 대단지 아파트 식음 서비스 시장에 처음 진출했다.","keyword":"아파트 급식 수주","url":"https://www.sedaily.com/article/20047964","source":"서울경제","published_at":"2026-05-26 07:01:00","sentiment":"positive","source_type":"news","is_new":true},{"id":"f04b6b18a12d","title":"마트 진열대 밖에서 번다…식품업계, B2B 신성장축","summary":"동원F&B 조미유통 매출, 일반식품 추월 풀무원 매출 30%는 급식·컨세션서 발생 CJ제일제당, 식품·물류 매출 비중 43%씩 내수 둔화·물가 압박 돌파구…매출 다변화[이데일리 신수정 기자] 국내 주요 식품기업들이 소비자 대상(B2C) 브랜드 제품 중심의 사업 구조에서 벗어나 식자재 유통과 급식, 물류 등 기업 간 거래(B2B) 영역으로 사업을 빠르게 확장하고 있다.\n\n(사진=롯데마트)25일 식품업계에 따르면 CJ제일제당, 동원F&B, 풀무원 등 주요 식품기업의 1분기 실적에서 조미유통과 식품서비스, 물류 사업이 차지하는 매출 비중이 크게 늘어난 것으로 나타났다.\n\n참치캔 등 소비자용 제품의 상징성은 유지되고 있지만, 동원홈푸드를 중심으로 한 식자재 유통과 급식 사업이 실질적인 매출 성장을 견인하는 구조다.","keyword":"B2B 사업 확장","url":"https://www.edaily.co.kr/news/newspath.asp?newsid=01669526645452528","source":"이데일리","published_at":"2026-05-25 13:28:00","sentiment":"positive","source_type":"news","is_new":true},{"id":"86465ffcfe3c","title":"[단독] 구미 라면 대전 벌어지나?… 연 매출 수조원대 식품기업 구미산단 입주 타진","summary":"유명 식품기업 A사, 구미산단 내 '라면 공장' 건립 물밑 협상 외국계 면발·라면 용기 제조사 등 2~3곳도 구미 부지 문의 쇄도 업계 \"라면 축제 시너지 폭발할 것\"… 구미시 \"문의 많은 건 사실, 적극 대응 중\" 경북 구미시가 '라면 성지'를 넘어 K-라면 수출 거점으로 떠오를 가능성이 커지고 있다.\n\n이미 구미에 생산 거점을 둔 농심에 이어 A사까지 대규모 투자를 단행할 경우, 산단 내에서 국내 대표 라면 브랜드 간 경쟁 구도가 형성될 가능성이 제기된다.\n\n라면 면발과 용기 등을 생산하는 외국계 기업을 포함해 2~3곳이 구미 내 공장 부지를 적극 문의 중인 것으로 알려졌다.","keyword":"라면 공장 투자","url":"https://www.imaeil.com/page/view/2026052513580903216","source":"매일신문","published_at":"2026-05-25 16:52:00","sentiment":"positive","source_type":"news","is_new":true},{"id":"b6124a6ffbca","title":"[단독] 中 ‘반입 불허’ 명단 오른 K푸드... CJ제일제당·사조대림 등","summary":"CJ제일제당, ‘해외 식품 생산기업 등록 문제’로 반입 불허 사조대림·엔셀 등은 ‘식품 첨가물 기준 부적합’ 코스맥스바이오·피러스 등은 ‘라벨 부적합’ 전문가 “中 규정 개정으로 대응력 중요” 중국 해관총서가 공개한 3월 반입 불허 식품 명단에 CJ제일제당과 사조대림 등 국내 식품사 제품이 다수 포함된 것으로 확인됐다.\n\n중국은 수입 식품 해외 생산 등록 관리 규정을 개정하고 한중 식품 안전 협력도 추진하고 있다.\n\n이런 상황에서 중국은 최근 수입 식품 해외 생산기업 등록 관리 규정을 개정했다.","keyword":"중국 반입 불허","url":"https://biz.chosun.com/distribution/food/2026/05/25/SK4ZDIQ2B5DHZFCUN3NEFH6VRI/?utm_medium=original&utm_campaign=biz","source":"조선비즈","published_at":"2026-05-25 06:03:00","sentiment":"negative","source_type":"news","is_new":true},{"id":"588310782332","title":"담합 잡는 자진신고제, 재발까진 못막아…비공개 탓 밀실 논란도(종합)","summary":"CJ제일제당, 19년 전 리니언시 혜택받고도 또 담합 25일 공정위 등에 따르면 리니언시는 1997년 도입된 이후로 담합을 적발하는 주요 수단으로 활용되고 있다.\n\n이후 공정위는 담합 사건에서 리니언시 적용 여부와 자진신고자를 밝히지 않고 있다.\n\n올해 설탕 담합, 밀가루 담합과 관련해서도 공정위는 리니언시를 정식으로 공개하지는 않았다.","keyword":"담합 자진신고제","url":"https://www.yna.co.kr/view/AKR20260524001651002?input=1195m","source":"연합뉴스","published_at":"2026-05-25 11:40:00","sentiment":"negative","source_type":"news","is_new":true}],"global_research":[],"us_movers":[],"stocks":[{"code":"280360","name":"롯데웰푸드","market":"KSP","price":121600.0,"change_pct":3.93,"market_cap":1119276198400.0,"fwd_pe":8.108768,"fwd_pb":null,"has_chart":true,"has_new":true,"news":[{"id":"1709674857286996549","title":"[인터뷰] 한 달 새 28만 개 팔린 '반값' 생식빵… \"전쟁으로 3년간 멈춘 개발, 오히려 전화위복\"","summary":"롯데 야심작 2000원대 프리미엄 식빵 '특허 유산균' 넣어 오래가는 촉촉함 초도 물량 10배로 키워 생산가 낮춰 신동빈 회장이 처음 아이디어 제시 \"여러 임직원 노력이 빛 봐서 기뻐요\" \"사실 양산하는 빵은 비싼 원료를 많이 못 쓰거든요.\n\n한데 이번에는 가성비를 챙기면서도 높은 품질의 생식빵을 만드는 게 목표여서 마가린 대신 가공 버터, 합성 감미료 대신 은은한 단맛과 감칠맛이 느껴지는 연유와 꿀을 넣었죠.\" 8,000원대 프리미엄 제품과 3,000원 미만 저가 보급형으로 양분된 국내 식빵 시장에 최근 가성비와 품질을 모두 충족해 도전장을 내민 식빵이 있다.\n\n장 연구원은 \"식빵을 자르는 대신 400g 통식빵으로 출시한 것도 이유가 있다\"며 \"허니브레드나 프렌치토스트 같은 레시피에 활용하기 좋은 데다 단 ...","url":"https://www.hankookilbo.com/news/article/A2026051714590002187?did=NA","published_at":"2026-05-23T14:00:00","sentiment":"positive","is_new":true},{"id":"1710342082847183444","title":"롯데웰푸드 설레임, 손시림 완화 패키지 적용 및 쿨리쉬 라인업 확대","summary":"파우치형 아이스크림 '설레임'이 미세발포 기술을 적용한 패키지로 손시림 현상을 개선하고 다가오는 빙과 성수기 공략에 나선다.\n\n롯데웰푸드는 출시 24주년을 맞은 아이스크림 브랜드 '설레임'에 신기술을 적용한 패키지를 도입하고, 신제품 2종을 출시했다고 밝혔다.\n\n롯데웰푸드는 빙과 성수기를 앞두고 설레임 쿨리쉬 신제품 2종(▶설레임 쿨리쉬 벨지안 초콜릿 ▶설레임 쿨리쉬 멜론소다)도 출시한다.","url":"https://www.sportschosun.com/life/2026-05-25/202605250100146410009897","published_at":"2026-05-25T10:12:00","sentiment":"positive","is_new":true}],"disclosures":[{"date":"2026-05-20T10:40:21","title":"기업설명회(IR)개최(안내공시)              ","url":"https://dart.fss.or.kr/dsaf001/main.do?rcpNo=20260520800143","is_new":false}],"reports":[],"consensus":{"Q":{"period":"2026년 2분기","latest":44480000000.0,"is_new":false,"series":[{"date":"2026-04-22","value":44030000000.0},{"date":"2026-04-24","value":44330000000.0},{"date":"2026-04-27","value":44230000000.0},{"date":"2026-04-30","value":43845454545.450005},{"date":"2026-05-11","value":43580000000.0},{"date":"2026-05-18","value":44480000000.0}]},"Y":{"period":"2026년","latest":187190000000.0,"is_new":false,"series":[{"date":"2026-04-22","value":173670000000.0},{"date":"2026-04-24","value":174770000000.0},{"date":"2026-04-27","value":175720000000.0},{"date":"2026-04-30","value":174927272727.27002},{"date":"2026-05-11","value":186290000000.0},{"date":"2026-05-18","value":187190000000.0}]}},"briefing":{"briefing":"이번 상승은 메이플스토리와의 협업을 통해 새로운 과자 제품을 출시한 소식에 힘입은 것으로 보입니다. 이러한 협업은 젊은 소비층을 겨냥한 마케팅 전략으로, 브랜드 인지도와 판매 증가에 긍정적인 영향을 미칠 것으로 기대됩니다.","content_url":"http://www.inews24.com/view/1969985","article_title":"\"게임·과자 경계 허문다\"…롯데웰푸드-메이플스토리 맞손","change_rate":3.93},"stk_flow":[{"date":"2026-05-22","외인":729464000,"개인":-1033471000,"기관":302335000},{"date":"2026-05-21","외인":-183061000,"개인":325755000,"기관":-161589000},{"date":"2026-05-20","외인":-452258000,"개인":-146016000,"기관":602859000},{"date":"2026-05-19","외인":-183321000,"개인":-482332000,"기관":668832000},{"date":"2026-05-18","외인":-388043000,"개인":203398000,"기관":188832000},{"date":"2026-05-15","외인":544700000,"개인":-944569000,"기관":420843000},{"date":"2026-05-14","외인":1536326000,"개인":-1198647000,"기관":-323229000}]},{"code":"006040","name":"동원산업","market":"KSP","price":37500.0,"change_pct":3.16,"market_cap":1655280712500.0,"fwd_pe":4.5138574,"fwd_pb":null,"has_chart":true,"has_new":false,"news":[],"disclosures":[{"date":"2026-05-18T16:36:13","title":"풍문또는보도에대한해명(미확정)              ","url":"https://dart.fss.or.kr/dsaf001/main.do?rcpNo=20260518800745","is_new":false},{"date":"2026-05-18T16:31:12","title":"최대주주등소유주식변동신고서              ","url":"https://dart.fss.or.kr/dsaf001/main.do?rcpNo=20260518800763","is_new":false},{"date":"2026-05-18T16:26:11","title":"주식등의대량보유상황보고서(일반)","url":"https://dart.fss.or.kr/dsaf001/main.do?rcpNo=20260518000314","is_new":false},{"date":"2026-05-18T12:10:44","title":"[기재정정]주식등의대량보유상황보고서(일반)","url":"https://dart.fss.or.kr/dsaf001/main.do?rcpNo=20260518000118","is_new":false},{"date":"2026-05-15T13:23:54","title":"분기보고서 (2026.03)","url":"https://dart.fss.or.kr/dsaf001/main.do?rcpNo=20260515000701","is_new":false}],"reports":[],"consensus":{"Q":{"period":"2026년 2분기","latest":127275000000.0,"is_new":false,"series":[{"date":"2026-04-22","value":135250000000.0},{"date":"2026-04-23","value":134900000000.0},{"date":"2026-04-30","value":134266666666.67},{"date":"2026-05-12","value":127275000000.0}]},"Y":{"period":"2026년","latest":552400000000.0,"is_new":false,"series":[{"date":"2026-04-22","value":563900000000.0},{"date":"2026-04-23","value":554400000000.0},{"date":"2026-04-30","value":554050000000.0},{"date":"2026-05-04","value":551400000000.0},{"date":"2026-05-12","value":548450000000.0},{"date":"2026-05-19","value":552400000000.0}]}},"briefing":{"briefing":"이번 상승은 '2026 코리아씨푸드쇼' 참가 소식에 따른 것으로, 소비자 체험형 부스를 통해 수산물 소비 확대에 기여할 것으로 기대됩니다. 이러한 마케팅 전략은 브랜드 인지도 향상과 매출 증대에 긍정적인 영향을 미칠 것으로 보입니다.","content_url":"https://www.donga.com/news/Economy/article/all/20260519/133952037/1","article_title":"동원산업, ‘2026 코리아씨푸드쇼’ 참가… “수산물 소비 확대 노력”","change_rate":3.16},"stk_flow":[{"date":"2026-05-22","외인":147146000,"개인":-653139000,"기관":506213000},{"date":"2026-05-21","외인":197926000,"개인":-338906000,"기관":40252000},{"date":"2026-05-20","외인":-1237138000,"개인":1328185000,"기관":-641922000},{"date":"2026-05-19","외인":-910089000,"개인":693124000,"기관":45918000},{"date":"2026-05-18","외인":-1401659000,"개인":1284371000,"기관":-96417000},{"date":"2026-05-15","외인":-428820000,"개인":220334000,"기관":161019000},{"date":"2026-05-14","외인":4353557000,"개인":-4313726000,"기관":932941000}]},{"code":"001680","name":"대상","market":"KSP","price":20000.0,"change_pct":2.51,"market_cap":692960500000.0,"fwd_pe":5.991612,"fwd_pb":null,"has_chart":true,"has_new":false,"news":[],"disclosures":[{"date":"2026-05-15T16:44:15","title":"분기보고서 (2026.03)","url":"https://dart.fss.or.kr/dsaf001/main.do?rcpNo=20260515002571","is_new":false}],"reports":[],"consensus":{"Q":{},"Y":{"period":"2026년","latest":192300000000.0,"is_new":false,"series":[{"date":"2026-05-19","value":192300000000.0}]}},"briefing":{"briefing":"주가 상승은 반려견 전용 영양 보조제 '닥터뉴토 듀얼캡슐' 3종 출시 소식에 긍정적인 반응을 얻은 것으로 보입니다. 이 신제품은 반려견의 건강 관리에 대한 수요 증가에 부응할 것으로 기대되며, 향후 매출 성장에 기여할 가능성이 있습니다.","content_url":"https://www.hankyung.com/article/202605196521g","article_title":"대상펫라이프 닥터뉴토, 반려견 영양 보조제 '듀얼캡슐' 3종 출시","change_rate":2.51},"stk_flow":[{"date":"2026-05-22","외인":599963000,"개인":-641264000,"기관":72453000},{"date":"2026-05-21","외인":522300000,"개인":94447000,"기관":-558674000},{"date":"2026-05-20","외인":-1215065000,"개인":1581066000,"기관":-396014000},{"date":"2026-05-19","외인":-1157793000,"개인":1331495000,"기관":-143943000},{"date":"2026-05-18","외인":-84512000,"개인":136610000,"기관":-60234000},{"date":"2026-05-15","외인":452757000,"개인":-516742000,"기관":86762000},{"date":"2026-05-14","외인":2524180000,"개인":-2847750000,"기관":325013000}]},{"code":"007310","name":"오뚜기","market":"KSP","price":350000.0,"change_pct":2.34,"market_cap":1402740500000.0,"fwd_pe":9.8350525,"fwd_pb":null,"has_chart":true,"has_new":true,"news":[{"id":"1709569653149405378","title":"[신상잇슈] 오뚜기 '칡냉면·쫄냉면'·삼립 하이면 '막국수' 2종","summary":"▲ 오뚜기는 전문점 스타일의 냉면을 간편하게 즐길 수 있는 신제품 '칡냉면'과 '쫄냉면'을 출시했다.\n\n▲ 삼립의 '하이면'은 여름 신제품 '홍비빔 막국수'와 '들기름 막국수' 2종을 출시했다.\n\n▲ 더벤티는 여름 컵빙수 메뉴 '마빙' 3종을 출시했다.","url":"https://www.yna.co.kr/view/AKR20260522048100030?input=1195m","published_at":"2026-05-23T07:00:00","sentiment":"positive","is_new":true}],"disclosures":[{"date":"2026-05-15T15:04:03","title":"분기보고서 (2026.03)","url":"https://dart.fss.or.kr/dsaf001/main.do?rcpNo=20260515001174","is_new":false}],"reports":[],"consensus":{"Q":{},"Y":{}},"briefing":{"briefing":"주가 상승은 신제품 출시와 관련된 긍정적인 소식이 영향을 미친 것으로 보입니다. 특히, 전문점 수준의 냉면과 저당 드레싱 제품 출시가 소비자들의 관심을 끌며 매출 증가에 기여할 것으로 기대됩니다.","content_url":"https://view.asiae.co.kr/article/2026052208264172095","article_title":"[오늘의신상]\"냉면 전문점 맛\"… 오뚜기, ‘칡냉면·쫄냉면’ 출시","change_rate":2.34},"stk_flow":[{"date":"2026-05-22","외인":438361000,"개인":-513412000,"기관":84787000},{"date":"2026-05-21","외인":-386464000,"개인":528294000,"기관":-136908000},{"date":"2026-05-20","외인":-492226000,"개인":781643000,"기관":-268357000},{"date":"2026-05-19","외인":149090000,"개인":-119933000,"기관":-26335000},{"date":"2026-05-18","외인":-419921000,"개인":406597000,"기관":10883000},{"date":"2026-05-15","외인":1314811000,"개인":-1279382000,"기관":-27112000},{"date":"2026-05-14","외인":1531990000,"개인":-2484326000,"기관":989138000}]},{"code":"004370","name":"농심","market":"KSP","price":400000.0,"change_pct":1.65,"market_cap":2433056800000.0,"fwd_pe":11.732294,"fwd_pb":null,"has_chart":true,"has_new":true,"news":[{"id":"1710442767672545621","title":"[단독] 구미 라면 대전 벌어지나?… 연 매출 수조원대 식품기업 구미산단 입주 타진","summary":"유명 식품기업 A사, 구미산단 내 '라면 공장' 건립 물밑 협상 외국계 면발·라면 용기 제조사 등 2~3곳도 구미 부지 문의 쇄도 업계 \"라면 축제 시너지 폭발할 것\"… 구미시 \"문의 많은 건 사실, 적극 대응 중\" 경북 구미시가 '라면 성지'를 넘어 K-라면 수출 거점으로 떠오를 가능성이 커지고 있다.\n\n이미 구미에 생산 거점을 둔 농심에 이어 A사까지 대규모 투자를 단행할 경우, 산단 내에서 국내 대표 라면 브랜드 간 경쟁 구도가 형성될 가능성이 제기된다.\n\n라면 면발과 용기 등을 생산하는 외국계 기업을 포함해 2~3곳이 구미 내 공장 부지를 적극 문의 중인 것으로 알려졌다.","url":"https://www.imaeil.com/page/view/2026052513580903216","published_at":"2026-05-25T16:52:00","sentiment":"positive","is_new":true},{"id":"1710394193752494095","title":"농심, 亞 최대 박람회 ‘타이펙스 아누가 2026’ 참가한다","summary":"26일부터 30일까지 5일간 태국 방콕에서 열리는 아시아 최대 규모 식품 박람회 ‘타이펙스 아누가(Thaifex ANUGA) 2026’에 단독 부스를 마련하고, 신라면, 신라면 툼바, 신라면 김치볶음면 등 글로벌 전략제품 홍보에 적극 나선다는 계획이다.\n\n동남아시아는 물론 글로벌 식품 트렌드를 한눈에 파악할 수 있는 아시아 최대 규모의 교역 장으로 꼽힌다.\n\n농심 관계자는 “지난해 유럽 아누가에 이어 올해는 아시아 시장의 관문인 태국 타이펙스 아누가에 참가해 전 세계 소비자들에게 ‘매콤한 행복’을 전하는 신라면의 매력을 알릴 것”이라고 말했다.","url":"https://sports.khan.co.kr/article/202605251338003","published_at":"2026-05-25T13:39:00","sentiment":"positive","is_new":true},{"id":"1709225083182125182","title":"제21회 광주식품대전 오는 24일까지 DJ센터서 열려","summary":"지역의 우수한 식문화를 선보이는 '제21회 광주식품대전'이 어제(21일)부터 오는 24일까지 광주 김대중컨벤션센터에서 개최됩니다.\n\n올해 행사는 농심과 하이트진로 등 대기업과 광주 향토 브랜드 등 300여 개 기업이 참여하며, 해외바이어 초청 수출상담회 규모를 지난해보다 2배 이상 확대해 비즈니스 기능을 강화했습니다.\n\n전시장에서는 디저트 큐레이션존과 로스터리 카페존 등 최신 식품 트렌드를 반영한 특별관이 운영되며, 광주 셰프 챌린지와 친환경 요리대전 등 다채로운 참여형 프로그램도 함께 열립니다.","url":"https://www.ikbc.co.kr/article/view/kbc202605220010","published_at":"2026-05-22T08:12:18","sentiment":"positive","is_new":true}],"disclosures":[{"date":"2026-05-15T14:03:58","title":"분기보고서 (2026.03)","url":"https://dart.fss.or.kr/dsaf001/main.do?rcpNo=20260515000865","is_new":false}],"reports":[{"broker":"유안타증권","title":"북미 수익성 회복, 유럽 확장 본격화","url":"https://ddi-cdn.deepsearch.com/research/company/2026/05/18/1707802237411135549/000-40e787bd0b5e33be034cfa0a6b3fce65bea662e9.pdf","date":"2026-05-18T10:00:10","summary":"유안타증권은 농심(004370)에 대해 목표주가 530,000원, 투자의견 매수를 유지했다. 1Q26 영업이익 674억원(YoY +20.3%)으로 컨센서스를 상회했으며, 원가율 하락이 수익성 개선의 핵심이었다. 북미는 가격 인상 효과로 OPM 8.0%(YoY +3.3%p)를 기록했고, 유럽법인 매출 인식 효과로 해외법인 매출이 YoY +23.1% 성장했다. 2Q26에는 미국 판매 흐름 개선과 유럽 확장이 지속되며 영업이익 YoY +40.5% 성장이 전망된다.","key_points":["1Q26 영업이익 674억원(YoY +20.3%, OPM 7.2%)으로 당사 추정치 및 컨센서스 상회 - 연결 매출원가율 YoY -2.0%p 개선이 핵심 동인","북미 1Q26 영업이익 133억원(YoY +75.4%), OPM 8.0%(YoY +3.3%p)로 수익성 대폭 개선, 2Q26 북미 매출 YoY +5.4% 성장 전망","유럽법인 1Q26 매출 372억원 기록, 신라면 툼바 영국에서 독일 등으로 입점 확대 중이며 2026F 유럽 매출 YoY +162% 성장 전망"],"is_new":false},{"broker":"LS증권","title":"해외 신제품 수요 확대","url":"https://ddi-cdn.deepsearch.com/research/company/2026/05/18/1707791611502661657/000-3dcbaf92445cb3fa62c67174ee2a4e80c9914e2f.pdf","date":"2026-05-18T09:17:57","summary":"LS증권은 농심의 1Q26 실적이 연결 매출액 9,340억원(+4.6% YoY), 영업이익 674억원(+20.3% YoY)으로 컨센서스를 12% 상회했다고 분석했다. 국내외 신제품 중심의 판매량 확대로 고정비 부담이 감소했으며, 서유럽 신제품 수출 고성장(+18.8%)과 유럽 법인의 신라면 툼바 인기가 두드러졌다. 2026년 연간 매출액 3조 7,241억원(+6.0% YoY), 영업이익 2,211억원(+20.2% YoY)을 전망하며, 투자의견 Buy와 목표주가 53만원을 유지했다.","key_points":["1Q26 영업이익 674억원으로 컨센서스 12% 상회, 국내외 신제품 판매량 확대에 따른 고정비 부담 감소가 주요 원인","라면 수출 +18.8% 고성장, 서유럽 신제품 판매 및 유럽 법인의 신라면 툼바 인기로 수출 커버리지 확대 지속","2026년 연간 영업이익 2,211억원(+20.2% YoY) 전망, 해외 법인 하반기 이익 성장 가속화 기대 및 목표주가 53만원 유지"],"is_new":false}],"consensus":{"Q":{"period":"2026년 2분기","latest":49492307692.31,"is_new":false,"series":[{"date":"2026-04-22","value":48418181818.18},{"date":"2026-04-23","value":47809090909.09},{"date":"2026-04-30","value":47408333333.329994},{"date":"2026-05-18","value":49492307692.31}]},"Y":{"period":"2026년","latest":212446153846.15002,"is_new":false,"series":[{"date":"2026-04-22","value":206109090909.09003},{"date":"2026-04-23","value":206436363636.36},{"date":"2026-04-30","value":207066666666.66998},{"date":"2026-05-18","value":212446153846.15002}]}},"briefing":{"briefing":"주가 상승은 최근 태국에서 열리는 식품 박람회 참가 소식과 신라면 로제 출시로 인한 K-푸드의 글로벌 입지 강화 기대감에 기인한 것으로 보입니다. 그러나 주가 변동률이 3% 미만으로 큰 변화는 없었으며, 담합 사건에 대한 과징금 부과 소식이 주요 이슈로 남아 있습니다.","content_url":"https://biz.heraldcorp.com/article/10743377","article_title":"농심, 亞 최대 식품 박람회 ‘타이펙스 아누가 2026’ 참가","change_rate":1.65},"stk_flow":[{"date":"2026-05-22","외인":3444112000,"개인":-3061249000,"기관":85538000},{"date":"2026-05-21","외인":1266070000,"개인":-1723930000,"기관":397267000},{"date":"2026-05-20","외인":1583361000,"개인":-2600636000,"기관":1286497000},{"date":"2026-05-19","외인":521170000,"개인":-2629941000,"기관":1915280000},{"date":"2026-05-18","외인":2606666000,"개인":-4730352000,"기관":1826265000},{"date":"2026-05-15","외인":11241017000,"개인":-12501011000,"기관":1279454000},{"date":"2026-05-14","외인":15606285000,"개인":-17864669000,"기관":2026150000}]},{"code":"097950","name":"CJ제일제당","market":"KSP","price":215000.0,"change_pct":1.18,"market_cap":3236649990000.0,"fwd_pe":7.2985673,"fwd_pb":null,"has_chart":true,"has_new":true,"news":[{"id":"1709955340738629671","title":"핵심 인재 전진배치…CJ제일제당, 글로벌 생산기지 가동 '임박'","summary":"CJ제일제당은 두 공장을 바탕으로 식품 사업의 글로벌 확장에 집중하겠다는 의지를 내비치고 있다.\n\n이를 바탕으로 CJ제일제당의 식품 사업 해외 매출 비중은 확대해나가고 있다.\n\nCJ제일제당의 식품 사업 부문 전체 매출 규모는 지난해 11조5221억원, 해외 매출은 5조9247억원으로 해외 매출 비중이 51.4%를 기록했다.","url":"https://view.asiae.co.kr/article/2026052011244867041","published_at":"2026-05-24T08:35:00","sentiment":"positive","is_new":true}],"disclosures":[{"date":"2026-05-15T15:54:07","title":"분기보고서 (2026.03)","url":"https://dart.fss.or.kr/dsaf001/main.do?rcpNo=20260515001768","is_new":false}],"reports":[],"consensus":{"Q":{"period":"2026년 2분기","latest":278184615384.62,"is_new":false,"series":[{"date":"2026-04-22","value":285645454545.44995},{"date":"2026-04-24","value":287141666666.67004},{"date":"2026-04-30","value":286592307692.31},{"date":"2026-05-11","value":284900000000.0},{"date":"2026-05-13","value":278800000000.0},{"date":"2026-05-18","value":278184615384.62}]},"Y":{"period":"2026년","latest":1295738461538.46,"is_new":false,"series":[{"date":"2026-04-22","value":1304400000000.0},{"date":"2026-04-24","value":1313500000000.0},{"date":"2026-04-30","value":1312678571428.57},{"date":"2026-05-11","value":1327850000000.0},{"date":"2026-05-13","value":1297200000000.0},{"date":"2026-05-18","value":1295738461538.46}]}},"briefing":{"briefing":"주가 상승은 최근 진행된 PGA 투어 '더 CJ컵'에서 비비고 브랜드를 통해 K-푸드를 전파하는 마케팅 활동이 긍정적인 반응을 얻고 있다는 소식에 기인한 것으로 보입니다. 그러나 주가 변동률이 3% 미만으로, 큰 변동은 없었던 점도 함께 고려해야 합니다.","content_url":"https://news.tf.co.kr/read/economy/2325038.htm","article_title":"CJ제일제당, CJ컵서 비비고로 K-푸드 전파…\"미식 경험 제공\"","change_rate":1.18},"stk_flow":[{"date":"2026-05-22","외인":650224000,"개인":541042000,"기관":-1218458000},{"date":"2026-05-21","외인":-3325847000,"개인":7554629000,"기관":-4521790000},{"date":"2026-05-20","외인":42656000,"개인":-259164000,"기관":59389000},{"date":"2026-05-19","외인":-3109541000,"개인":5258029000,"기관":-2783877000},{"date":"2026-05-18","외인":-2127292000,"개인":527692000,"기관":1636691000},{"date":"2026-05-15","외인":5905391000,"개인":-5022901000,"기관":-944097000},{"date":"2026-05-14","외인":16851239000,"개인":-18286775000,"기관":1672696000}]},{"code":"136480","name":"하림","market":"KSQ","price":3025.0,"change_pct":1.17,"market_cap":321284348550.0,"fwd_pe":null,"fwd_pb":null,"has_chart":true,"has_new":true,"news":[{"id":"1709598979781693650","title":"되살아난 ‘M&A 본능’…김홍국 하림 회장에 쏠리는 눈","summary":"저평가된 기업을 과감히 인수해 성장시키는 탁월한 능력을 앞세워 김 회장은 하림을 재계 30위권 그룹으로 키웠다.\n\n하림의 계열사 NS쇼핑은 기업회생 절차를 밟고 있는 홈플러스의 SSM(기업형 슈퍼마켓) 사업부인 ‘홈플러스 익스프레스’를 최종 인수하기로 했다.\n\n하림은 인수 직후 팬오션을 단숨에 흑자 기업으로 돌려세웠다.","url":"https://magazine.hankyung.com/business/article/202605145172b","published_at":"2026-05-23T08:58:00","sentiment":"positive","is_new":true},{"id":"1709569654760018172","title":"이원택 \"이재명과 원팀 전북 대도약\"…내발적 발전 제시","summary":"안호영 상임선대위원장 합류로 원팀 체제 구축 김관영 전 지사 비상계엄 사태 대응 강력 비판 제1호 공약 전북성장공사 설립해 경제 생태계 복원 새만금 국제 에너지 도시 조성으로 첨단 기업 유치 제9회 전국동시지방선거 공식 선거운동이 본격화한 가운데, 전북도지사 선거에 출마한 더불어민주당 기호 1번 이원택 후보가 이재명 대통령과 호흡을 맞출 적임자임을 자처하며 표심 공략에 나섰다.\n\n이 후보는 무소속 기호 7번 김관영 후보의 과거 비상계엄 사태 당시 행적을 강도 높게 비판하며 쟁점화를 시도하는 한편, 지역 기업 중심의 내발적 발전 전략과 전담 지원 조직 설립 등 구체적인 경제 공약을 발표했다.\n\n이 후보는 이번 선거의 핵심 슬로건으로 \"대통령도 민주당, 도지사도 민주당이어야 전북 대도약한다\"를 전면에 내걸었다.","url":"https://www.nocutnews.co.kr/news/6521815?utm_medium=article&utm_campaign=20260523070022","published_at":"2026-05-23T07:01:00","sentiment":"neutral","is_new":true},{"id":"1709251838617981412","title":"\"깊게 배어든 소스에 촉촉한 식감까지\" 하림, '칼집 닭가슴살' 출시","summary":"하림이 국내산 닭가슴살에 칼집 공법을 적용한 '칼집 닭가슴살' 6종을 출시했다고 22일 밝혔다.\n\n하림에 따르면 이번 신제품은 신선한 국내산 닭가슴살에 칼집을 깊숙하게 내어 속까지 소스가 고르게 흡수된다.\n\n'칼집 닭가슴살'은 ▲철판볶음맛 ▲간장찜닭맛 ▲사천짜장맛 ▲고추짬뽕맛 ▲마라탕맛 ▲깐풍기맛 등 총 6종으로 구성된다.","url":"https://www.newsis.com/view/NISX20260522_0003640571","published_at":"2026-05-22T09:57:26","sentiment":"positive","is_new":true}],"disclosures":[],"reports":[],"consensus":{"Q":{},"Y":{}},"briefing":{"briefing":"이 상승은 신제품 '칼집 닭가슴살' 출시와 관련된 긍정적인 소식에 기인한 것으로 보입니다. 그러나 주가 변동률이 크지 않았던 만큼, 시장의 반응은 다소 제한적이었던 것으로 판단됩니다.","content_url":"https://www.newsis.com/view/NISX20260522_0003640571","article_title":"\"깊게 배어든 소스에 촉촉한 식감까지\" 하림, '칼집 닭가슴살' 출시","change_rate":1.17},"stk_flow":[{"date":"2026-05-22","외인":-39069000,"개인":40856000,"기관":-2353000},{"date":"2026-05-21","외인":-659939000,"개인":656812000,"기관":-448000},{"date":"2026-05-20","외인":-773255000,"개인":1008392000,"기관":-245209000},{"date":"2026-05-19","외인":-17293000,"개인":16116000,"기관":1776000},{"date":"2026-05-18","외인":-64998000,"개인":54568000,"기관":1528000},{"date":"2026-05-15","외인":18424000,"개인":-24205000,"기관":1118000},{"date":"2026-05-14","외인":670438000,"개인":-662136000,"기관":574000}]},{"code":"003380","name":"하림지주","market":"KSQ","price":12170.0,"change_pct":0.91,"market_cap":1363108407570.0,"fwd_pe":null,"fwd_pb":null,"has_chart":true,"has_new":true,"news":[],"disclosures":[{"date":"2026-05-22T17:26:02","title":"임원ㆍ주요주주특정증권등소유상황보고서","url":"https://dart.fss.or.kr/dsaf001/main.do?rcpNo=20260522000616","is_new":true}],"reports":[],"consensus":{"Q":{},"Y":{}},"briefing":{"briefing":"이와 같은 상승세는 최근 대법원의 시세조종 관련 판결 소식과는 직접적인 연관이 없으나, 시장의 전반적인 긍정적인 분위기가 영향을 미쳤을 것으로 보입니다. 그러나 하림지주와 관련된 주요 이슈는 없었던 것으로 확인됩니다.","content_url":"https://www.newsis.com/view/NISX20260520_0003637484","article_title":"대법, 'SG발 주가조작' 라덕연 파기…\"장외파생도 시세조종죄 성립\"(종합)","change_rate":0.91},"stk_flow":[{"date":"2026-05-22","외인":-353318000,"개인":-232106000,"기관":282240000},{"date":"2026-05-21","외인":890140000,"개인":191837000,"기관":-662182000},{"date":"2026-05-20","외인":-672919000,"개인":-1031380000,"기관":265815000},{"date":"2026-05-19","외인":-10591000,"개인":-677816000,"기관":99353000},{"date":"2026-05-18","외인":53610000,"개인":-596004000,"기관":-49185000},{"date":"2026-05-15","외인":-2145459000,"개인":835918000,"기관":281130000},{"date":"2026-05-14","외인":6762805000,"개인":-4895131000,"기관":-2396446000}]},{"code":"271560","name":"오리온","market":"KSP","price":136900.0,"change_pct":0.37,"market_cap":5412496470800.0,"fwd_pe":10.374756,"fwd_pb":null,"has_chart":true,"has_new":true,"news":[{"id":"1710297044951896280","title":"'초코파이' 키운 용산 떠난다…오리온, 새로운 70년 '도곡동 시대'","summary":"오리온, 강남 도곡동 신사옥으로 이전 '초코파이 회사' 넘어 글로벌·바이오까지오리온이 70년 가까이 머무른 용산을 떠난다.\n\n글로벌 식품기업을 넘어 바이오까지 오리온은 1994년 이후 미디어·유통·외식 분야로 사업을 확장했다.\n\n오리온은 신사옥 이전이 마무리되면 기존 용산 사옥 부지 재개발에도 본격 나설 예정이다.","url":"https://view.asiae.co.kr/article/2026051921541593137","published_at":"2026-05-25T07:11:00","sentiment":"positive","is_new":true}],"disclosures":[{"date":"2026-05-19T14:58:24","title":"특수관계인으로부터부동산임차","url":"https://dart.fss.or.kr/dsaf001/main.do?rcpNo=20260519000144","is_new":false},{"date":"2026-05-15T15:14:04","title":"연결재무제표기준영업(잠정)실적(공정공시)              ","url":"https://dart.fss.or.kr/dsaf001/main.do?rcpNo=20260515801314","is_new":false},{"date":"2026-05-15T11:23:39","title":"분기보고서 (2026.03)","url":"https://dart.fss.or.kr/dsaf001/main.do?rcpNo=20260515000512","is_new":false}],"reports":[{"broker":"LS증권","title":"4월 잠정 실적 Review","url":"https://ddi-cdn.deepsearch.com/research/company/2026/05/19/1708138777387601928/000-43b08713127932f75dfeb7cb33d4ae178567f8cd.pdf","date":"2026-05-19T08:17:28","summary":"LS증권 박성호 애널리스트가 오리온(271560)의 2026년 4월 잠정 실적을 분석한 리포트. 4월 별도 합산 매출액 3,026억원(+14.4% YoY), 영업이익 469억원(+10.1% YoY)으로 중동 사태 영향을 높은 Q 성장으로 상쇄. 중국 법인의 간식점 채널 고성장, 러시아 법인의 수익성 개선이 두드러졌으며, 2026년 연간 매출액 3조 6,630억원(+9.9% YoY), 영업이익 6,344억원(+13.6% YoY) 전망. 목표주가 17만원, 투자의견 Buy 유지.","key_points":["4월 잠정 매출액 3,026억원(+14.4% YoY), 영업이익 469억원(+10.1% YoY, OPM 15.5%)으로 중동 사태 영향을 해외 법인의 높은 Q 성장으로 상쇄","중국 법인 간식점 채널 출고량 전년대비 +43% 증가, 채널 비중 35%까지 확대되며 구조적 성장세 지속. 러시아 법인은 코코아 원재료 단가 하락 반영으로 영업이익 +57.1% YoY 급증","2분기 중동 사태에 따른 제조원가 상승 본격화 예상되나, 월드컵 시즌 신제품 출시 및 코코아 원재료 단가 하락 효과로 상쇄 전망. 2026년 연간 영업이익 6,344억원(+13.6% YoY) 추정치 유지"],"is_new":false}],"consensus":{"Q":{"period":"2026년 2분기","latest":140206666666.66998,"is_new":true,"series":[{"date":"2026-04-22","value":141013333333.33002},{"date":"2026-04-24","value":139925000000.0},{"date":"2026-04-29","value":139320000000.0},{"date":"2026-04-30","value":140312500000.0},{"date":"2026-05-12","value":140213333333.33002},{"date":"2026-05-18","value":140146666666.66998},{"date":"2026-05-19","value":139893333333.33002},{"date":"2026-05-20","value":140100000000.0},{"date":"2026-05-22","value":140206666666.66998}]},"Y":{"period":"2026년","latest":650326666666.6699,"is_new":true,"series":[{"date":"2026-04-22","value":648260000000.0},{"date":"2026-04-24","value":648875000000.0},{"date":"2026-04-29","value":648720000000.0},{"date":"2026-04-30","value":648225000000.0},{"date":"2026-05-12","value":649480000000.0},{"date":"2026-05-18","value":649280000000.0},{"date":"2026-05-19","value":648820000000.0},{"date":"2026-05-20","value":649906666666.6699},{"date":"2026-05-22","value":650326666666.6699}]}},"briefing":{"briefing":"주가 상승은 본사 사옥 이전 소식과 함께 해외 매출 증가 기대감이 반영된 것으로 보입니다. 그러나 전체적인 변동은 크지 않았으며, 주요 이슈로는 중국 시장에서의 매출 성장과 관련된 긍정적인 전망이 있었습니다.","content_url":"https://news.tf.co.kr/read/economy/2324641.htm","article_title":"오리온, 70년 만에 서울 도곡동 사옥 이전…6월 첫 출근","change_rate":0.37},"stk_flow":[{"date":"2026-05-22","외인":5169580000,"개인":95057000,"기관":-5076832000},{"date":"2026-05-21","외인":8833883000,"개인":-1599852000,"기관":-7227980000},{"date":"2026-05-20","외인":1855615000,"개인":-184713000,"기관":-1539716000},{"date":"2026-05-19","외인":3169248000,"개인":-1709755000,"기관":-1418063000},{"date":"2026-05-18","외인":-3281767000,"개인":1553911000,"기관":1486965000},{"date":"2026-05-15","외인":551502000,"개인":-865461000,"기관":418741000},{"date":"2026-05-14","외인":518462000,"개인":-3511632000,"기관":3115330000}]},{"code":"003230","name":"삼양식품","market":"KSP","price":1315000.0,"change_pct":-0.3,"market_cap":9905914725000.0,"fwd_pe":14.757676,"fwd_pb":null,"has_chart":true,"has_new":true,"news":[{"id":"1709569146095800369","title":"\"악재에도 라면은 꿀맛\"…삼양식품 중심 강원 면류수출 또 신기록","summary":"강원 면류수출은 올해 넉 달간 1억 5668만여 달러로, 전년 동기(1억 4407만여 달러)보다 8.8% 성장했다.\n\n역대 1~4월 중 강원 면류수출의 최대 금액에 해당한다.\n\n원주 면류수출은 강원 면류수출의 90% 이상을 차지하는데, 올해 넉 달간 1억 5618만여 달러의 실적을 냈다.","url":"https://www.news1.kr/local/kangwon/6175773","published_at":"2026-05-23T07:00:00","sentiment":"positive","is_new":true},{"id":"1709564590968410290","title":"“방콕에서 만나는 불닭”…삼양, 타이펙스-아누가 식품박람회 참가","summary":"삼양식품은 ‘삼양 크레이브 랩’ 콘셉트로 체험형 부스를 운영한다.\n\n‘불닭, 맵, 탱글’ 등 삼양의 주요 브랜드를 독립된 ‘브랜드 랩’ 형태로 구현, 방문객들이 브랜드별 콘셉트와 제품 특징을 경험할 수 있다.\n\n삼양식품 관계자는 “단순히 제품을 전시하는 것을 넘어, 삼양식품의 다양한 브랜드를 직접 맛보고 즐기며 몰입감 있는 경험을 할 수 있도록 공간 구성에 중점을 뒀다”며, “불닭뿐 아니라 맵과 탱글 등 차별화된 브랜드를 통해 동남아 소비자와의 접점을 꾸준히 넓혀갈 것”이라고 전했다.","url":"https://www.sportsseoul.com/news/read/1610897","published_at":"2026-05-23T06:42:00","sentiment":"positive","is_new":true},{"id":"1709917393347809360","title":"주부에서 세계를 중독시킨 ‘불닭 여제’로…삼양식품 ‘김정수 매직’ [박영실의 이미지 브랜딩]","summary":"이후 2012년 전 세계를 매료시킨 ‘불닭볶음면’을 탄생시키며 삼양식품을 내수 기업에서 수출 주도형 글로벌 거물로 탈바꿈시켰다.\n\nBehavior 위기를 기회로 바꾼 김정수의 ‘현장 중심적 행동주의’ 경영 경험이 전무했던 주부가 매출 2조원을 돌파하는 글로벌 기업의 수장이 될 수 있었던 원동력은 집요하고도 과감한 ‘현장 중심적 행동주의’에 있다.\n\n이는 브랜드의 메가 히트가 가져다준 달콤한 축복인 동시에 글로벌 트렌드 변화나 예기치 못한 시장 규제에 직면했을 때 기업 전체가 흔들릴 수 있는 ‘달콤한 감옥’이 될 수 있다.","url":"https://magazine.hankyung.com/business/article/202605196682b","published_at":"2026-05-24T06:04:00","sentiment":"neutral","is_new":true}],"disclosures":[{"date":"2026-05-15T17:14:18","title":"기업설명회(IR)개최(안내공시)              ","url":"https://dart.fss.or.kr/dsaf001/main.do?rcpNo=20260515803157","is_new":false},{"date":"2026-05-15T16:54:16","title":"주식등의대량보유상황보고서(일반)","url":"https://dart.fss.or.kr/dsaf001/main.do?rcpNo=20260515002695","is_new":false}],"reports":[],"consensus":{"Q":{"period":"2026년 2분기","latest":175440000000.0,"is_new":false,"series":[{"date":"2026-04-22","value":167792307692.31},{"date":"2026-04-24","value":166242857142.86},{"date":"2026-04-30","value":165142857142.86},{"date":"2026-05-14","value":174306666666.66998},{"date":"2026-05-18","value":175440000000.0}]},"Y":{"period":"2026년","latest":725720000000.0,"is_new":false,"series":[{"date":"2026-04-22","value":692407142857.1399},{"date":"2026-04-24","value":692473333333.3301},{"date":"2026-04-30","value":690633333333.3301},{"date":"2026-05-14","value":724586666666.6699},{"date":"2026-05-18","value":725720000000.0}]}},"briefing":{"briefing":"이 하락세는 특별한 외부 요인 없이 진행되었으나, 김정수 부회장의 회장 승진 소식이 있었음을 알 수 있습니다. 향후 글로벌 사업 확대와 책임경영 강화에 대한 기대감이 존재하지만, 주가는 소폭 하락세를 보였습니다.","content_url":"https://biz.sbs.co.kr/article_hub/20000311950","article_title":"김정수, 우지 파동에서 불닭 회장까지 [CEO 업&다운]","change_rate":-0.3},"stk_flow":[{"date":"2026-05-22","외인":17620604000,"개인":10815921000,"기관":-27830418000},{"date":"2026-05-21","외인":6631078000,"개인":29992329000,"기관":-37990841000},{"date":"2026-05-20","외인":10184043000,"개인":-3270327000,"기관":-7116912000},{"date":"2026-05-19","외인":-11367854000,"개인":-12955241000,"기관":23353791000},{"date":"2026-05-18","외인":-9300655000,"개인":6684086000,"기관":6997241000},{"date":"2026-05-15","외인":-14479860000,"개인":-22916513000,"기관":37110328000},{"date":"2026-05-14","외인":55938104000,"개인":-98411279000,"기관":46825682000}]},{"code":"005180","name":"빙그레","market":"KSP","price":73300.0,"change_pct":0.27,"market_cap":679419972300.0,"fwd_pe":7.0370255,"fwd_pb":null,"has_chart":true,"has_new":false,"news":[],"disclosures":[{"date":"2026-05-15T16:29:13","title":"분기보고서 (2026.03)","url":"https://dart.fss.or.kr/dsaf001/main.do?rcpNo=20260515002363","is_new":false}],"reports":[],"consensus":{"Q":{"period":"2026년 2분기","latest":26366666666.67,"is_new":false,"series":[{"date":"2026-04-22","value":27050000000.0},{"date":"2026-04-30","value":27700000000.0},{"date":"2026-05-18","value":26366666666.67}]},"Y":{"period":"2026년","latest":101866666666.67,"is_new":false,"series":[{"date":"2026-04-22","value":99800000000.0},{"date":"2026-04-30","value":100200000000.0},{"date":"2026-05-18","value":101866666666.67}]}},"briefing":{"briefing":"주가는 소폭 상승했지만, 주요 이슈로는 바나나맛우유 도자기 세트의 크라우드 펀딩 시작과 김동만 사장의 해외사업 총괄 보임이 있습니다. 이러한 변화는 빙그레의 브랜드 강화와 해외 시장 확대 전략에 긍정적인 영향을 미칠 것으로 예상됩니다.","content_url":"https://www.hankyung.com/article/202605195685g","article_title":"빙그레, 와디즈서 '바나나맛우유' 도자기 세트 펀딩 개시","change_rate":0.27},"stk_flow":[{"date":"2026-05-22","외인":587000,"개인":484677000,"기관":-485707000},{"date":"2026-05-21","외인":-186514000,"개인":314407000,"기관":-129042000},{"date":"2026-05-20","외인":-556525000,"개인":565606000,"기관":21902000},{"date":"2026-05-19","외인":-806053000,"개인":-1660853000,"기관":2465965000},{"date":"2026-05-18","외인":-3123093000,"개인":3406263000,"기관":-570172000},{"date":"2026-05-15","외인":-7689764000,"개인":-8310474000,"기관":16150073000},{"date":"2026-05-14","외인":2042490000,"개인":-1904094000,"기관":-89080000}]}],"market_data":{"charts":[],"tables":[]}}