{"slug":"marine-shipping","wics_1st":"산업재","wics_2nd":"운송","wics_3rd":"해운사","trading_date":"2026-07-02","previous_trading_date":"2026-07-01","display_date":"2026-07-03","generated_at":"2026-07-03T06:53:04","sector_return":0.33,"ai_summary":["호르무즈 해협 원유 수송량 급증, 해운 물동량 회복 신호","HMM 홍해 대체 항로 운송 확대 및 본사 이전 본격화","SK해운 가스선 구조조정 성과, 해운업 수익성 개선 기대"],"news":[{"id":"9d36a4a51f2e","title":"호르무즈 해협 재개방 합의 2... 원유 수송량 전주대비 1218%↑","summary":"KMI 공급망리스크 리포트 운반선 늘어 기름값 안정 기대 미국과 이란의 호르무즈 해협 재개방 합의 발표 이후 선박 통항량이 회복세를 띠고 있는 것으로 조사됐다.\n\n주간 리포트에 따르면 6월 마지막 주 호르무즈 해협을 통과한 원유 수송량은 총 422만 DWT로, 전주 기록인 32만 DWT 대비 1218.8% 올랐다.\n\n호르무즈 해협 개방에 따라 사우디 얀부항으로의 주간 원유 수출량은 365만t을 기록, 전주 대비 14.8%(64여t) 감소한 모습을 보였다.","keyword":"호르무즈수송량","url":"http://www.fnnews.com/news/202607021830070328","source":"파이낸셜뉴스","published_at":"2026-07-02 18:31:00","sentiment":"positive","source_type":"news","is_new":true},{"id":"7a442cd579ad","title":"SK해운, 알짜 '가스선' 구조조정 통했다","summary":"가스선 영업이익률 50% 돌파 구조조정 완료 시 LNG선 32척·LPG선 14척 확보 한앤컴퍼니·김성익 대표, 이익창출력에 베팅 [파이낸셜뉴스] SK해운이 수익성이 높은 가스운반선 중심으로 선대를 재편하면서 이익창출력이 한층 강화되고 있다.\n\n정진원 NICE신용평가 기업평가본부 선임연구원은 \"회사는 탱커·벌크·벙커링 사업을 정리하고 에이치라인해운으로부터 LNG선 16척을 인수해 가스선 중심의 선대 구조조정을 진행하고 있다\"며 \"구조조정으로 선종 다각화 수준은 약화되나 총 LNG선 32척과 LPG선 14척을 확보해 국내외 가스선 시장지위가 제고될 것\"이라고 분석했다.\n\n이어 \"사업 구조조정이 완료되면 채산성이 높고 장기계약 중심의 수익안정성이 우수한 가스선 사업만 남고, 상대적으로 수익성이 낮았던 탱커·벌크· ...","keyword":"SK해운구조조정","url":"http://www.fnnews.com/news/202607010804409585","source":"","published_at":"2026-07-02T05:59:00","sentiment":"positive","source_type":"news","is_new":true},{"id":"b11897a971d2","title":"김현겸 팬스타그룹 회장, 5억원 규모 자사주 매","summary":"팬스타그룹의 코스닥 상장 계열사인 팬스타엔터프라이즈는 최대주주인 김현겸 회장이 주가 안정과 주주가치 제고를 위해 자사주 55만3098주를 장내에서 취득할 예정이라고 2일 공시했다.\n\n예정된 자사주 취득이 모두 완료되면 김 회장의 지분율은 19.72%로 높아진다.\n\n팬스타엔터프라이즈 관계자는 \"현재 주가가 기업가치 대비 저평가돼 있다고 판단한다\"며 \"최대주주의 자사주 취득은 책임경영을 강화하고 시장 신뢰를 높여 주가를 안정화하기 위한 것\"이라고 밝혔다.","keyword":"팬스타자사주매입","url":"https://www.kmib.co.kr/article/view.asp?arcid=0030053383&code=61141211","source":"국민일보","published_at":"2026-07-02 11:12:00","sentiment":"positive","source_type":"news","is_new":true},{"id":"db130ede4014","title":"팬스타그룹, 한·일 항로 컨테이너선 공동운항 참여","summary":"팬스타그룹은 한국근해수송협의회(KNFC)의 정식 공동운항 선사로 선정돼 지난 1일부터 한일 항로의 정기 컨테이너선 공동운항에 참여한다고 2일 밝혔다.\n\n한일 항로에서 크루즈와 고속페리, 로로(Ro-Ro) 화물선 등을 운영해 온 팬스타그룹은 이번 공동운항 참여를 계기로 컨테이너 정기선 사업을 본격화할 계획이다.\n\n팬스타는 공동운항 참여를 계기로 한일 항로를 넘어 중국과 동남아로 네트워크를 확장할 계획이다.","keyword":"팬스타공동운항","url":"http://www.kookje.co.kr/news2011/asp/newsbody.asp?code=0200&key=20260703.22011000558","source":"국제신문","published_at":"2026-07-02 18:44:00","sentiment":"positive","source_type":"news","is_new":true}],"global_research":[],"us_movers":[],"us_earnings":[],"stocks":[{"code":"067900","name":"와이엔텍","market":"KSQ","price":6360.0,"change_pct":-3.93,"market_cap":115749831240.0,"fwd_pe":null,"fwd_pb":null,"has_chart":true,"has_new":false,"news":[],"disclosures":[],"reports":[],"consensus":{"Q":{},"Y":{}},"briefing":{"briefing":"이러한 변동에 대한 공식적인 뉴스나 발표는 아직 확인되지 않았습니다.","content_url":"nan","article_title":"nan","change_rate":-3.93},"stk_flow":[{"date":"2026-07-02","외인":8994000,"개인":-339000,"기관":-11035000},{"date":"2026-07-01","외인":116875000,"개인":-98714000,"기관":-19208000},{"date":"2026-06-30","외인":-45068000,"개인":59182000,"기관":-14786000},{"date":"2026-06-29","외인":45166000,"개인":-57662000,"기관":-14123000},{"date":"2026-06-26","외인":-177275000,"개인":203117000,"기관":-19623000},{"date":"2026-06-25","외인":-131937000,"개인":150298000,"기관":-22220000},{"date":"2026-06-24","외인":-199255000,"개인":220090000,"기관":-16946000}]},{"code":"028670","name":"팬오션","market":"KSP","price":4970.0,"change_pct":3.54,"market_cap":2656810474640.0,"fwd_pe":6.0352154,"fwd_pb":null,"has_chart":true,"has_new":true,"news":[{"id":"1724049420087070781","title":"SK해운, 알짜 '가스선' 구조조정 통했다","summary":"가스선 영업이익률 50% 돌파 구조조정 완료 시 LNG선 32척·LPG선 14척 확보 한앤컴퍼니·김성익 대표, 이익창출력에 베팅 [파이낸셜뉴스] SK해운이 수익성이 높은 가스운반선 중심으로 선대를 재편하면서 이익창출력이 한층 강화되고 있다.\n\n정진원 NICE신용평가 기업평가본부 선임연구원은 \"회사는 탱커·벌크·벙커링 사업을 정리하고 에이치라인해운으로부터 LNG선 16척을 인수해 가스선 중심의 선대 구조조정을 진행하고 있다\"며 \"구조조정으로 선종 다각화 수준은 약화되나 총 LNG선 32척과 LPG선 14척을 확보해 국내외 가스선 시장지위가 제고될 것\"이라고 분석했다.\n\n이어 \"사업 구조조정이 완료되면 채산성이 높고 장기계약 중심의 수익안정성이 우수한 가스선 사업만 남고, 상대적으로 수익성이 낮았던 탱커·벌크· ...","url":"http://www.fnnews.com/news/202607010804409585","published_at":"2026-07-02T05:59:00","sentiment":"positive","is_new":true}],"disclosures":[{"date":"2026-06-29T17:12:50","title":"신규시설투자등              ","url":"https://dart.fss.or.kr/dsaf001/main.do?rcpNo=20260629801140","is_new":false},{"date":"2026-06-29T15:37:36","title":"동일인등출자계열회사와의상품ㆍ용역거래","url":"https://dart.fss.or.kr/dsaf001/main.do?rcpNo=20260629000357","is_new":false},{"date":"2026-06-25T09:31:25","title":"최대주주등소유주식변동신고서              ","url":"https://dart.fss.or.kr/dsaf001/main.do?rcpNo=20260625800144","is_new":false}],"reports":[],"consensus":{"Q":{"period":"2026년 3분기","latest":145814285714.28998,"is_new":false,"series":[{"date":"2026-06-02","value":144646153846.15002},{"date":"2026-06-08","value":145030769230.77},{"date":"2026-06-23","value":145600000000.0},{"date":"2026-06-30","value":145814285714.28998}]},"Y":{"period":"2026년","latest":572000000000.0,"is_new":false,"series":[{"date":"2026-06-02","value":565000000000.0},{"date":"2026-06-08","value":565846153846.15},{"date":"2026-06-23","value":568857142857.1399},{"date":"2026-06-30","value":572000000000.0}]}},"briefing":{"briefing":"이번 상승은 해상운임 급등과 함께 2조 5000억 원 규모의 선박 투자 소식이 긍정적으로 작용한 것으로 보입니다. 이러한 투자와 해운업계의 긍정적인 전망이 팬오션의 실적 개선에 기여할 것으로 기대됩니다.","content_url":"https://www.sedaily.com/article/20062144","article_title":"“팬오션, 4년 만에 매출 6조원 탈환 예상…해상운임 급등 영향”","change_rate":3.54},"stk_flow":[{"date":"2026-07-02","외인":-1145243000,"개인":-2183211000,"기관":3258747000},{"date":"2026-07-01","외인":779475000,"개인":-1367261000,"기관":508195000},{"date":"2026-06-30","외인":-366250000,"개인":-702547000,"기관":1126325000},{"date":"2026-06-29","외인":-161627000,"개인":-721462000,"기관":887713000},{"date":"2026-06-26","외인":1759698000,"개인":-1538648000,"기관":51736000},{"date":"2026-06-25","외인":-8277000,"개인":456639000,"기관":-451419000},{"date":"2026-06-24","외인":1691586000,"개인":-960192000,"기관":-876999000}]},{"code":"011200","name":"HMM","market":"KSP","price":19100.0,"change_pct":2.36,"market_cap":18015845227000.0,"fwd_pe":15.604575,"fwd_pb":null,"has_chart":true,"has_new":true,"news":[{"id":"1724238952409468979","title":"호르무즈 해협 재개방 합의 2... 원유 수송량 전주대비 1218%↑","summary":"KMI 공급망리스크 리포트 운반선 늘어 기름값 안정 기대 미국과 이란의 호르무즈 해협 재개방 합의 발표 이후 선박 통항량이 회복세를 띠고 있는 것으로 조사됐다.\n\n주간 리포트에 따르면 6월 마지막 주 호르무즈 해협을 통과한 원유 수송량은 총 422만 DWT로, 전주 기록인 32만 DWT 대비 1218.8% 올랐다.\n\n호르무즈 해협 개방에 따라 사우디 얀부항으로의 주간 원유 수출량은 365만t을 기록, 전주 대비 14.8%(64여t) 감소한 모습을 보였다.","url":"http://www.fnnews.com/news/202607021830070328","published_at":"2026-07-02T18:31:00","sentiment":"positive","is_new":true},{"id":"1724117799934235252","title":"홍해 대체 항로서 11척째 원유 운송…해수부 \"수급 안정화\"","summary":"호르무즈 안정화까지 대체 항로 활용 정진형 기자 = 미국과 이란의 종전 합의에도 산발적 무력 충돌이 일어나는 호르무즈 해협 대신 홍해를 통해 국내로 원유를 옮기는 한국 선박이 11척으로 늘었다.\n\n해양수산부는 2일 오전 10시 기준 한국 선박 한 척이 홍해를 안전하게 통과해 국내로 원유를 운송하고 있다고 밝혔다.\n\n해당 선박은 사우디아라비아 얀부항에서 원유를 적재한 후 홍해를 빠져나왔다.","url":"https://www.newsis.com/view/NISX20260702_0003693050","published_at":"2026-07-02T10:30:00","sentiment":"positive","is_new":true},{"id":"1724294758299472201","title":"HMM 9월부터 본격 이전…남은 과제는?","summary":"본사 주소지를 부산으로 옮긴 HMM이 임시 사옥을 마련하는 등 본격적인 이전 작업에 나섰습니다.\n\n서면교차로 인근에 들어선 24층 높이의 한 건물, 본사 주소지를 부산으로 옮긴 HMM이 임시 사옥으로 유력하게 검토 중인 곳입니다.\n\n특히 HMM은 북항에 '상징 건물'급 사옥 건설을 공언했지만 해양수산부와 부산항만공사, 부산시가 함께 머리를 맞대야 할 상황입니다.","url":"https://news.kbs.co.kr/news/pc/view/view.do?ncd=8601013&ref=A","published_at":"2026-07-02T22:08:00","sentiment":"neutral","is_new":true}],"disclosures":[{"date":"2026-06-26T15:40:21","title":"단일판매ㆍ공급계약체결              ","url":"https://dart.fss.or.kr/dsaf001/main.do?rcpNo=20260626800701","is_new":false}],"reports":[],"consensus":{"Q":{"period":"2026년 3분기","latest":277300000000.0,"is_new":false,"series":[{"date":"2026-06-02","value":268575000000.0},{"date":"2026-06-08","value":277325000000.0},{"date":"2026-06-23","value":277838461538.46},{"date":"2026-06-30","value":277300000000.0}]},"Y":{"period":"2026년","latest":1055484615384.62,"is_new":false,"series":[{"date":"2026-06-02","value":1011941666666.6699},{"date":"2026-06-08","value":1029358333333.3301},{"date":"2026-06-23","value":1037715384615.38},{"date":"2026-06-30","value":1055484615384.62}]}},"briefing":{"briefing":"주가 상승은 본사의 부산 이전과 관련된 긍정적인 소식이 영향을 미친 것으로 보입니다. 또한, HMM이 글로벌 ESG 평가에서 3년 연속 최고 등급을 유지한 점도 투자자들에게 긍정적인 신호로 작용했을 것으로 예상됩니다.","content_url":"https://www.ddaily.co.kr/page/view/2026062611072447293","article_title":"HMM, 글로벌 ESG 평가 3년 연속 최상위권…에코바디스 플래티넘 획득","change_rate":2.36},"stk_flow":[{"date":"2026-07-02","외인":6044000000,"개인":-12499249000,"기관":6501440000},{"date":"2026-07-01","외인":-311136000,"개인":746082000,"기관":-488182000},{"date":"2026-06-30","외인":-6058762000,"개인":6259431000,"기관":-408531000},{"date":"2026-06-29","외인":-1781249000,"개인":-2037669000,"기관":4048592000},{"date":"2026-06-26","외인":-6594101000,"개인":6758124000,"기관":-182563000},{"date":"2026-06-25","외인":-1204122000,"개인":2937728000,"기관":-1794518000},{"date":"2026-06-24","외인":-1546599000,"개인":2675621000,"기관":-1243829000}]},{"code":"005880","name":"대한해운","market":"KSP","price":1855.0,"change_pct":-0.64,"market_cap":598696315700.0,"fwd_pe":4.215909,"fwd_pb":null,"has_chart":true,"has_new":false,"news":[],"disclosures":[],"reports":[],"consensus":{"Q":{"period":"2026년 3분기","latest":57340000000.0,"is_new":false,"series":[{"date":"2026-06-02","value":59750000000.0},{"date":"2026-06-30","value":57340000000.0}]},"Y":{"period":"2026년","latest":243260000000.0,"is_new":false,"series":[{"date":"2026-06-02","value":246200000000.0},{"date":"2026-06-30","value":243260000000.0}]}},"briefing":{"briefing":"이번 하락은 해운업계의 전반적인 긍정적인 전망에도 불구하고, 향후 운임 하락 가능성이 제기된 데 따른 것으로 보입니다. 특히, 3분기 수요가 앞당겨질 것이라는 예측이 주가에 부정적인 영향을 미친 것으로 분석됩니다.","content_url":"https://biz.heraldcorp.com/article/10794828","article_title":"호르무즈 해협 개방에도 운임은 고공행진…해운사 2분기 ‘순항’","change_rate":-0.64},"stk_flow":[{"date":"2026-07-02","외인":1335660000,"개인":175252000,"기관":-1538941000},{"date":"2026-07-01","외인":378474000,"개인":-387203000,"기관":-2410000},{"date":"2026-06-30","외인":-563683000,"개인":347263000,"기관":213638000},{"date":"2026-06-29","외인":792215000,"개인":-1262570000,"기관":467073000},{"date":"2026-06-26","외인":677698000,"개인":-727782000,"기관":6166000},{"date":"2026-06-25","외인":336313000,"개인":-333214000,"기관":-15244000},{"date":"2026-06-24","외인":737687000,"개인":-758579000,"기관":23354000}]}],"market_data":{"charts":[{"title":"BDI","unit":"pt","last_date":"2026-06-03","last_val":3124.0,"prev_val":3037.0,"chg":87.0,"chg_pct":2.86,"series":[{"d":"2026-07-01","v":2562.0},{"d":"2026-06-30","v":2501.0},{"d":"2026-06-29","v":2490.0},{"d":"2026-06-26","v":2524.0},{"d":"2026-06-25","v":2591.0},{"d":"2026-06-24","v":2634.0},{"d":"2026-06-23","v":2667.0},{"d":"2026-06-22","v":2684.0},{"d":"2026-06-19","v":2722.0},{"d":"2026-06-18","v":2659.0},{"d":"2026-06-17","v":2653.0},{"d":"2026-06-16","v":2670.0},{"d":"2026-06-15","v":2720.0},{"d":"2026-06-12","v":2729.0},{"d":"2026-06-11","v":2729.0},{"d":"2026-06-10","v":2771.0},{"d":"2026-06-09","v":2818.0},{"d":"2026-06-08","v":2916.0},{"d":"2026-06-05","v":2981.0},{"d":"2026-06-04","v":3037.0},{"d":"2026-06-03","v":3124.0}]},{"title":"SCFI","unit":"pt","last_date":"2026-06-05","last_val":2726.48,"prev_val":2985.22,"chg":-258.74,"chg_pct":-8.67,"series":[{"d":"2026-06-26","v":3239.64},{"d":"2026-06-18","v":3121.69},{"d":"2026-06-12","v":2985.22},{"d":"2026-06-05","v":2726.48}]},{"title":"Fuel Oil","unit":"CNY/t","last_date":"2026-07-02","last_val":2882.0,"prev_val":2957.0,"chg":-75.0,"chg_pct":-2.54,"series":[{"d":"2026-06-01","v":3838.0},{"d":"2026-06-02","v":3933.0},{"d":"2026-06-03","v":3918.0},{"d":"2026-06-04","v":3908.0},{"d":"2026-06-05","v":3837.0},{"d":"2026-06-08","v":3901.0},{"d":"2026-06-09","v":3798.0},{"d":"2026-06-10","v":3693.0},{"d":"2026-06-11","v":3771.0},{"d":"2026-06-12","v":3678.0},{"d":"2026-06-15","v":3451.0},{"d":"2026-06-16","v":3335.0},{"d":"2026-06-17","v":3198.0},{"d":"2026-06-22","v":3124.0},{"d":"2026-06-23","v":3046.0},{"d":"2026-06-24","v":3026.0},{"d":"2026-06-25","v":2940.0},{"d":"2026-06-26","v":2980.0},{"d":"2026-06-29","v":2959.0},{"d":"2026-06-30","v":2969.0},{"d":"2026-07-01","v":2957.0},{"d":"2026-07-02","v":2882.0}]}],"tables":[]}}